{
  "generated_at": "2026-05-12T14:49:03.589124+00:00",
  "quotes": [
    {
      "symbol": "spy.us",
      "name": "S&P 500 ETF",
      "asset": "equity",
      "close": 733.562,
      "date": "2026-05-12",
      "time": "16:34:01",
      "status": "live"
    },
    {
      "symbol": "qqq.us",
      "name": "Nasdaq 100 ETF",
      "asset": "equity",
      "close": 703.37,
      "date": "2026-05-12",
      "time": "16:34:02",
      "status": "live"
    },
    {
      "symbol": "tlt.us",
      "name": "20+ Year Treasury ETF",
      "asset": "bond",
      "close": 85.035,
      "date": "2026-05-12",
      "time": "16:34:01",
      "status": "live"
    },
    {
      "symbol": "gld.us",
      "name": "Gold ETF",
      "asset": "gold",
      "close": 429.445,
      "date": "2026-05-12",
      "time": "16:34:04",
      "status": "live"
    },
    {
      "symbol": "uso.us",
      "name": "Oil ETF",
      "asset": "commodity",
      "close": 144.1022,
      "date": "2026-05-12",
      "time": "16:34:04",
      "status": "live"
    },
    {
      "symbol": "uup.us",
      "name": "US Dollar ETF",
      "asset": "fx",
      "close": 27.48,
      "date": "2026-05-12",
      "time": "16:33:30",
      "status": "live"
    }
  ],
  "status": "live",
  "errors": [],
  "source": "Stooq delayed quote CSV with built-in fallback values"
}
