{
  "generated_at": "2026-05-22T20:06:09.893296+00:00",
  "items": [
    {
      "id": "bls_macro-cpi-u-333-02-2026-4-a0f27630",
      "date": "5月22日",
      "time": "20:06",
      "sourceId": "bls_macro",
      "source": "美国劳工统计局公开数据 API",
      "sourceUrl": "https://api.bls.gov/publicAPI/v2/timeseries/data/",
      "sourceBrief": "通胀、就业和工资数据的官方来源，是利率路径和资产估值的重要输入。",
      "originalTitle": "美国 CPI-U 全项目最新读数：333.02 指数（2026年4月）",
      "originalSummary": "美国劳工统计局官方序列 CUUR0000SA0 在 2026年4月 的读数为 333.02 指数；较上一期变化 +2.81。这是判断利率、股票、债券、黄金和汇率的重要通胀输入。",
      "avatar": "B",
      "score": 98,
      "category": "macro",
      "horizon": "short",
      "asset": "equity bond gold fx",
      "title": "美国 CPI-U 全项目最新读数：333.02 指数（2026年4月）",
      "summary": "美国劳工统计局官方序列 CUUR0000SA0 在 2026年4月 的读数为 333.02 指数；较上一期变化 +2.81。这是判断利率、股票、债券、黄金和汇率的重要通胀输入。",
      "aiBrief": "AI速读：这条信息主要讲通胀，优先级很高。它可能通过利率预期、美元方向和估值折现率影响股票、债券、黄金、汇率，需要和原文、价格反应以及后续数据一起确认。",
      "watchPoints": [
        "美债收益率和美元是否同步反应",
        "降息或加息概率是否重新定价",
        "股票、债券、黄金、汇率是否出现同向价格确认",
        "同主题是否出现第二个一手信源确认"
      ],
      "tags": [
        "宏观",
        "S级信源",
        "股票、债券、黄金、汇率"
      ],
      "reason": "来自 美国劳工统计局公开数据 API 的高优先级信息，可能影响股票、债券、黄金、汇率。评分综合信源等级、关键词命中、发布时间和影响资产范围。",
      "sourceRank": "S级",
      "absorbed": "尚未完全消化",
      "shortTerm": "短期观察该信息是否在股票、债券、黄金、汇率价格中形成确认。",
      "midTerm": "中期结合后续数据和资金流，判断宏观主线是否延续。",
      "longTerm": "长期意义取决于它是否改变利率、盈利、通胀或风险溢价的基准假设。",
      "decision": "仅作为研究和风控输入，不作为单独交易信号；等待价格、数据和信源交叉确认。"
    },
    {
      "id": "fed_press-agencies-publish-resolution-plan-feedback-letters-fo-df1ee811",
      "date": "5月22日",
      "time": "20:00",
      "sourceId": "fed_press",
      "source": "美联储新闻稿",
      "sourceUrl": "https://www.federalreserve.gov/newsevents/pressreleases/bcreg20260522a.htm",
      "sourceBrief": "美国货币政策、金融监管和利率预期的一手信源。",
      "originalTitle": "Agencies publish resolution plan feedback letters for certain domestic and foreign banking organizations",
      "originalSummary": "Agencies publish resolution plan feedback letters for certain domestic and foreign banking organizations",
      "avatar": "F",
      "score": 98,
      "category": "risk",
      "horizon": "short",
      "asset": "equity bond gold fx",
      "title": "美联储新闻稿更新：全球流动性和金融稳定",
      "summary": "美联储新闻稿发布与全球流动性和金融稳定相关的新信息，系统将其归入风险类影响因素，重点观察它对股票、债券、黄金、汇率的传导。正式决策应结合原文链接、后续数据和价格确认。",
      "aiBrief": "AI速读：这条信息主要讲全球流动性和金融稳定，优先级很高。它可能通过波动率、信用利差和避险需求影响股票、债券、黄金、汇率，需要和原文、价格反应以及后续数据一起确认。",
      "watchPoints": [
        "VIX、信用利差和美元是否同时上行",
        "避险资产是否获得持续买盘",
        "股票、债券、黄金、汇率是否出现同向价格确认",
        "同主题是否出现第二个一手信源确认"
      ],
      "tags": [
        "风险",
        "S级信源",
        "股票、债券、黄金、汇率"
      ],
      "reason": "来自 美联储新闻稿 的高优先级信息，可能影响股票、债券、黄金、汇率。评分综合信源等级、关键词命中、发布时间和影响资产范围。",
      "sourceRank": "S级",
      "absorbed": "尚未完全消化",
      "shortTerm": "短期观察该信息是否在股票、债券、黄金、汇率价格中形成确认。",
      "midTerm": "中期结合后续数据和资金流，判断风险主线是否延续。",
      "longTerm": "长期意义取决于它是否改变利率、盈利、通胀或风险溢价的基准假设。",
      "decision": "仅作为研究和风控输入，不作为单独交易信号；等待价格、数据和信源交叉确认。"
    },
    {
      "id": "ecb_press-decisions-taken-by-the-governing-council-of-the-ecb--60fcecbc",
      "date": "5月22日",
      "time": "13:00",
      "sourceId": "ecb_press",
      "source": "欧洲央行新闻与讲话",
      "sourceUrl": "https://www.ecb.europa.eu//press/govcdec/otherdec/2026/html/ecb.gc260522~a4812a8f23.en.html",
      "sourceBrief": "欧元区货币政策、通胀判断和金融稳定的一手信源。",
      "originalTitle": "Decisions taken by the Governing Council of the ECB (in addition to decisions setting interest rates)",
      "originalSummary": "",
      "avatar": "E",
      "score": 98,
      "category": "macro",
      "horizon": "short",
      "asset": "equity bond gold fx",
      "title": "欧洲央行新闻与讲话更新：利率政策和央行路径",
      "summary": "欧洲央行新闻与讲话发布与利率政策和央行路径相关的新信息，系统将其归入宏观类影响因素，重点观察它对股票、债券、黄金、汇率的传导。正式决策应结合原文链接、后续数据和价格确认。",
      "aiBrief": "AI速读：这条信息主要讲利率政策和央行路径，优先级很高。它可能通过利率预期、美元方向和估值折现率影响股票、债券、黄金、汇率，需要和原文、价格反应以及后续数据一起确认。",
      "watchPoints": [
        "美债收益率和美元是否同步反应",
        "降息或加息概率是否重新定价",
        "股票、债券、黄金、汇率是否出现同向价格确认",
        "同主题是否出现第二个一手信源确认"
      ],
      "tags": [
        "宏观",
        "S级信源",
        "股票、债券、黄金、汇率"
      ],
      "reason": "来自 欧洲央行新闻与讲话 的高优先级信息，可能影响股票、债券、黄金、汇率。评分综合信源等级、关键词命中、发布时间和影响资产范围。",
      "sourceRank": "S级",
      "absorbed": "尚未完全消化",
      "shortTerm": "短期观察该信息是否在股票、债券、黄金、汇率价格中形成确认。",
      "midTerm": "中期结合后续数据和资金流，判断宏观主线是否延续。",
      "longTerm": "长期意义取决于它是否改变利率、盈利、通胀或风险溢价的基准假设。",
      "decision": "仅作为研究和风控输入，不作为单独交易信号；等待价格、数据和信源交叉确认。"
    },
    {
      "id": "treasury_press-treasury-targets-hizballah-aligned-officials-obstruc-0bba4cd1",
      "date": "5月22日",
      "time": "20:06",
      "sourceId": "treasury_press",
      "source": "美国财政部新闻稿",
      "sourceUrl": "https://home.treasury.gov/news/press-releases/sb0505",
      "sourceBrief": "财政、发债、制裁和跨境资金政策的官方来源，会影响美债、美元和风险偏好。",
      "originalTitle": "Treasury Targets Hizballah-Aligned Officials Obstructing Peace and Disarmament",
      "originalSummary": "",
      "avatar": "T",
      "score": 90,
      "category": "bond",
      "horizon": "mid",
      "asset": "bond equity fx gold",
      "title": "美国财政部新闻稿更新：财政融资和美债供给",
      "summary": "美国财政部新闻稿发布与财政融资和美债供给相关的新信息，系统将其归入债券类影响因素，重点观察它对股票、债券、黄金、汇率的传导。正式决策应结合原文链接、后续数据和价格确认。",
      "aiBrief": "AI速读：这条信息主要讲财政融资和美债供给，优先级很高。它可能通过收益率曲线、期限溢价和美元流动性影响股票、债券、黄金、汇率，需要和原文、价格反应以及后续数据一起确认。",
      "watchPoints": [
        "长端收益率是否突破近期区间",
        "财政融资或拍卖需求是否继续恶化",
        "股票、债券、黄金、汇率是否出现同向价格确认",
        "同主题是否出现第二个一手信源确认"
      ],
      "tags": [
        "债券",
        "S级信源",
        "股票、债券、黄金、汇率"
      ],
      "reason": "来自 美国财政部新闻稿 的高优先级信息，可能影响股票、债券、黄金、汇率。评分综合信源等级、关键词命中、发布时间和影响资产范围。",
      "sourceRank": "S级",
      "absorbed": "尚未完全消化",
      "shortTerm": "短期观察该信息是否在股票、债券、黄金、汇率价格中形成确认。",
      "midTerm": "中期结合后续数据和资金流，判断债券主线是否延续。",
      "longTerm": "长期意义取决于它是否改变利率、盈利、通胀或风险溢价的基准假设。",
      "decision": "仅作为研究和风控输入，不作为单独交易信号；等待价格、数据和信源交叉确认。"
    },
    {
      "id": "bloomberg_markets-bond-traders-bet-fed-under-warsh-will-hike-rates-thi-5948e349",
      "date": "5月22日",
      "time": "14:19",
      "sourceId": "bloomberg_markets",
      "source": "Bloomberg Markets",
      "sourceUrl": "https://www.bloomberg.com/news/articles/2026-05-22/traders-bet-fed-under-warsh-will-hike-rates-by-end-of-this-year",
      "sourceBrief": "全球市场新闻源，适合捕捉宏观、地缘、央行和资产价格叙事。",
      "originalTitle": "Bond Traders Bet Fed Under Warsh Will Hike Rates This Year",
      "originalSummary": "Bond traders are fully pricing in an interest-rate hike by the Federal Reserve this year, a sign of conviction in the market that Chair Kevin Warsh will need to move quickly to combat inflation.",
      "avatar": "L",
      "score": 89,
      "category": "macro",
      "horizon": "short",
      "asset": "equity bond gold fx",
      "title": "Bloomberg Markets观察：通胀压力和实际利率",
      "summary": "Bloomberg Markets报道了与通胀压力和实际利率相关的市场线索，系统将其归入宏观类影响因素。它更适合帮助理解市场叙事和资金情绪，仍需用一手数据和价格反应验证。",
      "aiBrief": "AI速读：这是一条媒体解释源，主要讲通胀压力和实际利率，优先级很高。它有助于理解市场正在交易什么叙事，但不能替代官方数据；需要观察股票、债券、黄金、汇率是否给出价格确认。",
      "watchPoints": [
        "美债收益率和美元是否同步反应",
        "降息或加息概率是否重新定价",
        "股票、债券、黄金、汇率是否出现同向价格确认",
        "同主题是否出现第二个一手信源确认"
      ],
      "tags": [
        "宏观",
        "媒体解释源",
        "股票、债券、黄金、汇率"
      ],
      "reason": "来自 Bloomberg Markets 的高优先级信息，可能影响股票、债券、黄金、汇率。评分综合信源等级、关键词命中、发布时间和影响资产范围。",
      "sourceRank": "A级",
      "absorbed": "尚未完全消化",
      "shortTerm": "短期观察该信息是否在股票、债券、黄金、汇率价格中形成确认。",
      "midTerm": "中期结合后续数据和资金流，判断宏观主线是否延续。",
      "longTerm": "长期意义取决于它是否改变利率、盈利、通胀或风险溢价的基准假设。",
      "decision": "仅作为研究和风控输入，不作为单独交易信号；等待价格、数据和信源交叉确认。"
    },
    {
      "id": "eia_energy-the-regional-differences-in-gasoline-prices-this-mem-7b822f0f",
      "date": "5月22日",
      "time": "14:00",
      "sourceId": "eia_energy",
      "source": "美国能源信息署能源日报",
      "sourceUrl": "https://www.eia.gov/todayinenergy/detail.php?id=67706",
      "sourceBrief": "能源供需、库存和价格压力的官方线索，主要影响原油、通胀和能源股。",
      "originalTitle": "The regional differences in gasoline prices this Memorial Day",
      "originalSummary": "Against the backdrop of a nationwide increase in gasoline prices, regional dynamics including local supply and demand conditions, state fuel specifications, and state taxes influence the different prices drivers see at the pump.",
      "avatar": "E",
      "score": 88,
      "category": "commodity",
      "horizon": "short",
      "asset": "commodity equity bond",
      "title": "美国能源信息署能源日报更新：通胀压力和实际利率",
      "summary": "美国能源信息署能源日报发布与通胀压力和实际利率相关的新信息，系统将其归入商品类影响因素，重点观察它对股票、债券、商品的传导。正式决策应结合原文链接、后续数据和价格确认。",
      "aiBrief": "AI速读：这条信息主要讲通胀压力和实际利率，优先级很高。它可能通过通胀预期、成本压力和周期资产表现影响股票、债券、商品，需要和原文、价格反应以及后续数据一起确认。",
      "watchPoints": [
        "库存、供给和现货价格是否同向变化",
        "通胀预期是否被重新抬升",
        "股票、债券、商品是否出现同向价格确认",
        "同主题是否出现第二个一手信源确认"
      ],
      "tags": [
        "商品",
        "S级信源",
        "股票、债券、商品"
      ],
      "reason": "来自 美国能源信息署能源日报 的高优先级信息，可能影响股票、债券、商品。评分综合信源等级、关键词命中、发布时间和影响资产范围。",
      "sourceRank": "S级",
      "absorbed": "尚未完全消化",
      "shortTerm": "短期观察该信息是否在股票、债券、商品价格中形成确认。",
      "midTerm": "中期结合后续数据和资金流，判断商品主线是否延续。",
      "longTerm": "长期意义取决于它是否改变利率、盈利、通胀或风险溢价的基准假设。",
      "decision": "仅作为研究和风控输入，不作为单独交易信号；等待价格、数据和信源交叉确认。"
    },
    {
      "id": "sec_press-sec-rescinds-policy-regarding-denials-of-settlements-3b5fea73",
      "date": "5月18日",
      "time": "16:33",
      "sourceId": "sec_press",
      "source": "美国 SEC 新闻稿",
      "sourceUrl": "https://www.sec.gov/newsroom/press-releases/2026-45-sec-rescinds-policy-regarding-denials-settlements-enforcement-actions",
      "sourceBrief": "资本市场监管、执法和披露风险的一手信源。",
      "originalTitle": "SEC Rescinds Policy Regarding Denials of Settlements in Enforcement Actions",
      "originalSummary": "The Securities and Exchange Commission today rescinded a policy, codified in Rule 202.5(e) of its informal rules of procedures, stating that when it chooses to settle an enforcement action in which a sanction is imposed, it will not settle unless the…",
      "avatar": "S",
      "score": 87,
      "category": "equity",
      "horizon": "mid",
      "asset": "equity",
      "title": "美国 SEC 新闻稿更新：资本市场监管和公司风险",
      "summary": "美国 SEC 新闻稿发布与资本市场监管和公司风险相关的新信息，系统将其归入股票类影响因素，重点观察它对股票的传导。正式决策应结合原文链接、后续数据和价格确认。",
      "aiBrief": "AI速读：这条信息主要讲资本市场监管和公司风险，优先级很高。它可能通过盈利预期、估值风险和资金偏好影响股票，需要和原文、价格反应以及后续数据一起确认。",
      "watchPoints": [
        "相关板块 ETF 和龙头股是否放量反应",
        "盈利预期或监管风险是否扩散",
        "股票是否出现同向价格确认",
        "同主题是否出现第二个一手信源确认"
      ],
      "tags": [
        "股票",
        "S级信源",
        "股票"
      ],
      "reason": "来自 美国 SEC 新闻稿 的高优先级信息，可能影响股票。评分综合信源等级、关键词命中、发布时间和影响资产范围。",
      "sourceRank": "S级",
      "absorbed": "尚未完全消化",
      "shortTerm": "短期观察该信息是否在股票价格中形成确认。",
      "midTerm": "中期结合后续数据和资金流，判断股票主线是否延续。",
      "longTerm": "长期意义取决于它是否改变利率、盈利、通胀或风险溢价的基准假设。",
      "decision": "仅作为研究和风控输入，不作为单独交易信号；等待价格、数据和信源交叉确认。"
    },
    {
      "id": "ft_home-wall-street-bets-on-2026-rate-rise-as-kevin-warsh-ta-c34fab4f",
      "date": "5月22日",
      "time": "16:15",
      "sourceId": "ft_home",
      "source": "Financial Times",
      "sourceUrl": "https://www.ft.com/content/7a0b2b54-c62b-4498-8b8d-512ef7f2cb5d",
      "sourceBrief": "国际高可信财经媒体，适合跟踪政策、企业、地缘和长期结构变化。",
      "originalTitle": "Wall Street bets on 2026 rate rise as Kevin Warsh takes charge of the Fed",
      "originalSummary": "Markets expect US central bank to lift borrowing costs by end of year as Iran war intensifies inflation",
      "avatar": "F",
      "score": 86,
      "category": "macro",
      "horizon": "short",
      "asset": "equity bond gold fx",
      "title": "Financial Times观察：通胀压力和实际利率",
      "summary": "Financial Times报道了与通胀压力和实际利率相关的市场线索，系统将其归入宏观类影响因素。它更适合帮助理解市场叙事和资金情绪，仍需用一手数据和价格反应验证。",
      "aiBrief": "AI速读：这是一条媒体解释源，主要讲通胀压力和实际利率，优先级很高。它有助于理解市场正在交易什么叙事，但不能替代官方数据；需要观察股票、债券、黄金、汇率是否给出价格确认。",
      "watchPoints": [
        "美债收益率和美元是否同步反应",
        "降息或加息概率是否重新定价",
        "股票、债券、黄金、汇率是否出现同向价格确认",
        "同主题是否出现第二个一手信源确认"
      ],
      "tags": [
        "宏观",
        "媒体解释源",
        "股票、债券、黄金、汇率"
      ],
      "reason": "来自 Financial Times 的高优先级信息，可能影响股票、债券、黄金、汇率。评分综合信源等级、关键词命中、发布时间和影响资产范围。",
      "sourceRank": "A级",
      "absorbed": "尚未完全消化",
      "shortTerm": "短期观察该信息是否在股票、债券、黄金、汇率价格中形成确认。",
      "midTerm": "中期结合后续数据和资金流，判断宏观主线是否延续。",
      "longTerm": "长期意义取决于它是否改变利率、盈利、通胀或风险溢价的基准假设。",
      "decision": "仅作为研究和风控输入，不作为单独交易信号；等待价格、数据和信源交叉确认。"
    },
    {
      "id": "cnbc_markets-consumer-sentiment-hits-fresh-record-low-in-may-as-i-df89139d",
      "date": "5月22日",
      "time": "16:13",
      "sourceId": "cnbc_markets",
      "source": "CNBC 市场新闻",
      "sourceUrl": "https://www.cnbc.com/2026/05/22/consumer-sentiment-hits-fresh-record-low-in-may-as-iran-war-fuels-inflation-worries.html",
      "sourceBrief": "美国主流财经媒体，适合跟踪股市、科技股、政策交易和投资者情绪。",
      "originalTitle": "Consumer sentiment hits fresh record low in May as Iran war fuels inflation worries",
      "originalSummary": "Consumer sentiment has tumbled to a fresh record low in May as fears of higher prices grow due to the U.S.-Iran war and elevated oil prices.",
      "avatar": "N",
      "score": 82,
      "category": "macro",
      "horizon": "short",
      "asset": "equity bond gold fx",
      "title": "CNBC 市场新闻观察：通胀压力和实际利率",
      "summary": "CNBC 市场新闻报道了与通胀压力和实际利率相关的市场线索，系统将其归入宏观类影响因素。它更适合帮助理解市场叙事和资金情绪，仍需用一手数据和价格反应验证。",
      "aiBrief": "AI速读：这是一条媒体解释源，主要讲通胀压力和实际利率，值得跟踪。它有助于理解市场正在交易什么叙事，但不能替代官方数据；需要观察股票、债券、黄金、汇率是否给出价格确认。",
      "watchPoints": [
        "美债收益率和美元是否同步反应",
        "降息或加息概率是否重新定价",
        "股票、债券、黄金、汇率是否出现同向价格确认",
        "同主题是否出现第二个一手信源确认"
      ],
      "tags": [
        "宏观",
        "媒体解释源",
        "股票、债券、黄金、汇率"
      ],
      "reason": "来自 CNBC 市场新闻 的高优先级信息，可能影响股票、债券、黄金、汇率。评分综合信源等级、关键词命中、发布时间和影响资产范围。",
      "sourceRank": "A级",
      "absorbed": "尚未完全消化",
      "shortTerm": "短期观察该信息是否在股票、债券、黄金、汇率价格中形成确认。",
      "midTerm": "中期结合后续数据和资金流，判断宏观主线是否延续。",
      "longTerm": "长期意义取决于它是否改变利率、盈利、通胀或风险溢价的基准假设。",
      "decision": "仅作为研究和风控输入，不作为单独交易信号；等待价格、数据和信源交叉确认。"
    },
    {
      "id": "bis_press-basel-committee-agrees-to-publish-report-on-informat-b16d18a3",
      "date": "5月20日",
      "time": "15:00",
      "sourceId": "bis_press",
      "source": "国际清算银行新闻",
      "sourceUrl": "https://www.bis.org/press/p260520.htm",
      "sourceBrief": "全球央行协调、金融稳定和银行体系风险的高质量线索。",
      "originalTitle": "Basel Committee agrees to publish report on information and communication technology risk management, progresses cryptoasset targeted review, considers targeted updates on liquidity risk principles",
      "originalSummary": "Agrees to publish range of practices report on information and communication technology risk management. Progresses its targeted review of the prudential standard for banks' cryptoasset exposures. Considers targeted updates of its principles on liquidity risk.",
      "avatar": "I",
      "score": 82,
      "category": "risk",
      "horizon": "short",
      "asset": "equity bond gold fx",
      "title": "国际清算银行新闻更新：全球流动性和金融稳定",
      "summary": "国际清算银行新闻发布与全球流动性和金融稳定相关的新信息，系统将其归入风险类影响因素，重点观察它对股票、债券、黄金、汇率的传导。正式决策应结合原文链接、后续数据和价格确认。",
      "aiBrief": "AI速读：这条信息主要讲全球流动性和金融稳定，值得跟踪。它可能通过波动率、信用利差和避险需求影响股票、债券、黄金、汇率，需要和原文、价格反应以及后续数据一起确认。",
      "watchPoints": [
        "VIX、信用利差和美元是否同时上行",
        "避险资产是否获得持续买盘",
        "股票、债券、黄金、汇率是否出现同向价格确认",
        "同主题是否出现第二个一手信源确认"
      ],
      "tags": [
        "风险",
        "A级信源",
        "股票、债券、黄金、汇率"
      ],
      "reason": "来自 国际清算银行新闻 的高优先级信息，可能影响股票、债券、黄金、汇率。评分综合信源等级、关键词命中、发布时间和影响资产范围。",
      "sourceRank": "A级",
      "absorbed": "尚未完全消化",
      "shortTerm": "短期观察该信息是否在股票、债券、黄金、汇率价格中形成确认。",
      "midTerm": "中期结合后续数据和资金流，判断风险主线是否延续。",
      "longTerm": "长期意义取决于它是否改变利率、盈利、通胀或风险溢价的基准假设。",
      "decision": "仅作为研究和风控输入，不作为单独交易信号；等待价格、数据和信源交叉确认。"
    },
    {
      "id": "bis_stats-statistical-release-bis-international-banking-statis-ca6a13b5",
      "date": "4月30日",
      "time": "07:28",
      "sourceId": "bis_stats",
      "source": "国际清算银行统计发布",
      "sourceUrl": "https://www.bis.org/statistics/rppb2604.htm",
      "sourceBrief": "全球流动性、跨境银行和杠杆周期的中长期监测来源。",
      "originalTitle": "Statistical release: BIS international banking statistics and global liquidity indicators at end-December 2025",
      "originalSummary": "Cross-border bank credit grew by 11% year-on-year, the highest annual growth rate since Q1 2008. Bank credit to emerging market and developing economies (EMDEs) expanded by $42 billion in Q4 2025, which brought its annual growth rate up to 7%. The BIS global liquidity indicators show that foreign currency credit in US dollars and euros continued to grow robustly, both globally and in EMDEs.",
      "avatar": "D",
      "score": 78,
      "category": "risk",
      "horizon": "short",
      "asset": "equity bond gold fx",
      "title": "国际清算银行统计发布更新：全球流动性和金融稳定",
      "summary": "国际清算银行统计发布发布与全球流动性和金融稳定相关的新信息，系统将其归入风险类影响因素，重点观察它对股票、债券、黄金、汇率的传导。正式决策应结合原文链接、后续数据和价格确认。",
      "aiBrief": "AI速读：这条信息主要讲全球流动性和金融稳定，值得跟踪。它可能通过波动率、信用利差和避险需求影响股票、债券、黄金、汇率，需要和原文、价格反应以及后续数据一起确认。",
      "watchPoints": [
        "VIX、信用利差和美元是否同时上行",
        "避险资产是否获得持续买盘",
        "股票、债券、黄金、汇率是否出现同向价格确认",
        "同主题是否出现第二个一手信源确认"
      ],
      "tags": [
        "风险",
        "A级信源",
        "股票、债券、黄金、汇率"
      ],
      "reason": "来自 国际清算银行统计发布 的高优先级信息，可能影响股票、债券、黄金、汇率。评分综合信源等级、关键词命中、发布时间和影响资产范围。",
      "sourceRank": "A级",
      "absorbed": "部分消化",
      "shortTerm": "短期观察该信息是否在股票、债券、黄金、汇率价格中形成确认。",
      "midTerm": "中期结合后续数据和资金流，判断风险主线是否延续。",
      "longTerm": "长期意义取决于它是否改变利率、盈利、通胀或风险溢价的基准假设。",
      "decision": "仅作为研究和风控输入，不作为单独交易信号；等待价格、数据和信源交叉确认。"
    },
    {
      "id": "guardian_business-kevin-warsh-sworn-in-as-fed-chair-as-trump-faces-bac-a016f428",
      "date": "5月22日",
      "time": "17:16",
      "sourceId": "guardian_business",
      "source": "Guardian Business",
      "sourceUrl": "https://www.theguardian.com/us-news/2026/may/22/trump-not-focused-on-economy-poll",
      "sourceBrief": "英国商业与政策新闻源，适合补充欧洲经济、监管和社会政策影响。",
      "originalTitle": "Kevin Warsh sworn in as Fed chair as Trump faces backlash over economy",
      "originalSummary": "Former Wall Street banker takes over amid growing concern over cost of living – and disapproval of Trump’s agenda US politics live – latest updates Kevin Warsh has been sworn in as chair of the US Federal Reserve , tasked with steering the world’s largest economy as the Trump administration faces mounting pressure over Americans’ financial wellbeing. Warsh, handpicked by Donald Trump, takes charge of the powerful central bank as it comes under extraordinary pressure from the US president to cut interest rates, even as prices climb. Continue reading...",
      "avatar": "G",
      "score": 77,
      "category": "macro",
      "horizon": "short",
      "asset": "equity bond gold fx",
      "title": "Guardian Business观察：利率政策和央行路径",
      "summary": "Guardian Business报道了与利率政策和央行路径相关的市场线索，系统将其归入宏观类影响因素。它更适合帮助理解市场叙事和资金情绪，仍需用一手数据和价格反应验证。",
      "aiBrief": "AI速读：这是一条媒体解释源，主要讲利率政策和央行路径，值得跟踪。它有助于理解市场正在交易什么叙事，但不能替代官方数据；需要观察股票、债券、黄金、汇率是否给出价格确认。",
      "watchPoints": [
        "美债收益率和美元是否同步反应",
        "降息或加息概率是否重新定价",
        "股票、债券、黄金、汇率是否出现同向价格确认",
        "同主题是否出现第二个一手信源确认"
      ],
      "tags": [
        "宏观",
        "媒体解释源",
        "股票、债券、黄金、汇率"
      ],
      "reason": "来自 Guardian Business 的高优先级信息，可能影响股票、债券、黄金、汇率。评分综合信源等级、关键词命中、发布时间和影响资产范围。",
      "sourceRank": "B级",
      "absorbed": "部分消化",
      "shortTerm": "短期观察该信息是否在股票、债券、黄金、汇率价格中形成确认。",
      "midTerm": "中期结合后续数据和资金流，判断宏观主线是否延续。",
      "longTerm": "长期意义取决于它是否改变利率、盈利、通胀或风险溢价的基准假设。",
      "decision": "仅作为研究和风控输入，不作为单独交易信号；等待价格、数据和信源交叉确认。"
    },
    {
      "id": "census_indicators-monthly-wholesale-trade-sales-and-inventories-6983bea5",
      "date": "5月8日",
      "time": "14:00",
      "sourceId": "census_indicators",
      "source": "美国人口普查局经济指标",
      "sourceUrl": "https://www.census.gov/wholesale/index.html",
      "sourceBrief": "零售、库存、贸易和制造业等实体经济指标的官方来源。",
      "originalTitle": "Monthly Wholesale Trade: Sales and Inventories",
      "originalSummary": "March 2026 sales of merchant wholesalers were $772.2 billion, up 2.8 percent (+/- 0.4 percent) from last month. End-of-month inventories were $932.8 billion, up 1.3 percent (+/- 0.2 percent) from last month. March 2026: +1.3 % Change in Inventories February 2026 (r): +0.9 % Change in Inventories",
      "avatar": "C",
      "score": 76,
      "category": "macro",
      "horizon": "short",
      "asset": "equity bond gold fx",
      "title": "美国人口普查局经济指标更新：消费需求和企业收入",
      "summary": "美国人口普查局经济指标发布与消费需求和企业收入相关的新信息，系统将其归入宏观类影响因素，重点观察它对股票、债券、黄金、汇率的传导。正式决策应结合原文链接、后续数据和价格确认。",
      "aiBrief": "AI速读：这条信息主要讲消费需求和企业收入，值得跟踪。它可能通过利率预期、美元方向和估值折现率影响股票、债券、黄金、汇率，需要和原文、价格反应以及后续数据一起确认。",
      "watchPoints": [
        "美债收益率和美元是否同步反应",
        "降息或加息概率是否重新定价",
        "股票、债券、黄金、汇率是否出现同向价格确认",
        "同主题是否出现第二个一手信源确认"
      ],
      "tags": [
        "宏观",
        "S级信源",
        "股票、债券、黄金、汇率"
      ],
      "reason": "来自 美国人口普查局经济指标 的高优先级信息，可能影响股票、债券、黄金、汇率。评分综合信源等级、关键词命中、发布时间和影响资产范围。",
      "sourceRank": "S级",
      "absorbed": "部分消化",
      "shortTerm": "短期观察该信息是否在股票、债券、黄金、汇率价格中形成确认。",
      "midTerm": "中期结合后续数据和资金流，判断宏观主线是否延续。",
      "longTerm": "长期意义取决于它是否改变利率、盈利、通胀或风险溢价的基准假设。",
      "decision": "仅作为研究和风控输入，不作为单独交易信号；等待价格、数据和信源交叉确认。"
    },
    {
      "id": "marketwatch_top-kevin-warsh-walks-into-a-trap-where-the-fed-can-t-cu-f8fb08d1",
      "date": "5月22日",
      "time": "20:01",
      "sourceId": "marketwatch_top",
      "source": "MarketWatch 头条",
      "sourceUrl": "https://www.marketwatch.com/story/kevin-warsh-walks-into-a-trap-where-the-fed-cant-cut-rates-even-if-it-wants-to-8475e97c?mod=mw_rss_topstories",
      "sourceBrief": "面向投资者的市场新闻源，适合观察美股、基金和个人投资者叙事。",
      "originalTitle": "Kevin Warsh walks into a trap where the Fed can’t cut rates even if it wants to",
      "originalSummary": "Kevin Warsh is becoming Federal Reserve chair at a pivotal moment for the U.S. economy — forcing him to be something other than the disruptor he hoped to be.",
      "avatar": "M",
      "score": 75,
      "category": "macro",
      "horizon": "short",
      "asset": "equity bond gold fx",
      "title": "MarketWatch 头条观察：宏观数据和政策预期",
      "summary": "MarketWatch 头条报道了与宏观数据和政策预期相关的市场线索，系统将其归入宏观类影响因素。它更适合帮助理解市场叙事和资金情绪，仍需用一手数据和价格反应验证。",
      "aiBrief": "AI速读：这是一条媒体解释源，主要讲宏观数据和政策预期，值得跟踪。它有助于理解市场正在交易什么叙事，但不能替代官方数据；需要观察股票、债券、黄金、汇率是否给出价格确认。",
      "watchPoints": [
        "美债收益率和美元是否同步反应",
        "降息或加息概率是否重新定价",
        "股票、债券、黄金、汇率是否出现同向价格确认",
        "同主题是否出现第二个一手信源确认"
      ],
      "tags": [
        "宏观",
        "媒体解释源",
        "股票、债券、黄金、汇率"
      ],
      "reason": "来自 MarketWatch 头条 的高优先级信息，可能影响股票、债券、黄金、汇率。评分综合信源等级、关键词命中、发布时间和影响资产范围。",
      "sourceRank": "A级",
      "absorbed": "部分消化",
      "shortTerm": "短期观察该信息是否在股票、债券、黄金、汇率价格中形成确认。",
      "midTerm": "中期结合后续数据和资金流，判断宏观主线是否延续。",
      "longTerm": "长期意义取决于它是否改变利率、盈利、通胀或风险溢价的基准假设。",
      "decision": "仅作为研究和风控输入，不作为单独交易信号；等待价格、数据和信源交叉确认。"
    },
    {
      "id": "bbc_business-trump-wants-new-fed-chair-to-be-totally-independent-a2394b60",
      "date": "5月22日",
      "time": "18:16",
      "sourceId": "bbc_business",
      "source": "BBC Business",
      "sourceUrl": "https://www.bbc.com/news/articles/cvgz311dq3ko?at_medium=RSS&at_campaign=rss",
      "sourceBrief": "国际商业新闻源，适合补充宏观、消费、企业和英国/欧洲风险线索。",
      "originalTitle": "Trump wants new Fed chair to be 'totally independent'",
      "originalSummary": "The US president piled major pressure on Kevin Warsh's predecessor to cut interest rates.",
      "avatar": "B",
      "score": 75,
      "category": "macro",
      "horizon": "short",
      "asset": "equity bond gold fx",
      "title": "BBC Business观察：利率政策和央行路径",
      "summary": "BBC Business报道了与利率政策和央行路径相关的市场线索，系统将其归入宏观类影响因素。它更适合帮助理解市场叙事和资金情绪，仍需用一手数据和价格反应验证。",
      "aiBrief": "AI速读：这是一条媒体解释源，主要讲利率政策和央行路径，值得跟踪。它有助于理解市场正在交易什么叙事，但不能替代官方数据；需要观察股票、债券、黄金、汇率是否给出价格确认。",
      "watchPoints": [
        "美债收益率和美元是否同步反应",
        "降息或加息概率是否重新定价",
        "股票、债券、黄金、汇率是否出现同向价格确认",
        "同主题是否出现第二个一手信源确认"
      ],
      "tags": [
        "宏观",
        "媒体解释源",
        "股票、债券、黄金、汇率"
      ],
      "reason": "来自 BBC Business 的高优先级信息，可能影响股票、债券、黄金、汇率。评分综合信源等级、关键词命中、发布时间和影响资产范围。",
      "sourceRank": "B级",
      "absorbed": "部分消化",
      "shortTerm": "短期观察该信息是否在股票、债券、黄金、汇率价格中形成确认。",
      "midTerm": "中期结合后续数据和资金流，判断宏观主线是否延续。",
      "longTerm": "长期意义取决于它是否改变利率、盈利、通胀或风险溢价的基准假设。",
      "decision": "仅作为研究和风控输入，不作为单独交易信号；等待价格、数据和信源交叉确认。"
    },
    {
      "id": "boj_whatsnew-5-21-2e22683b",
      "date": "5月22日",
      "time": "08:30",
      "sourceId": "boj_whatsnew",
      "source": "日本央行最新信息",
      "sourceUrl": "http://www.boj.or.jp/about/press/kaiken_2026/kk260522a.pdf",
      "sourceBrief": "日本利率、日元和全球套息交易风险的重要来源。",
      "originalTitle": "【記者会見】小枝審議委員（福岡、5月21日分）",
      "originalSummary": "",
      "avatar": "J",
      "score": 72,
      "category": "macro",
      "horizon": "mid",
      "asset": "bond fx equity gold",
      "title": "日本央行最新信息更新：日本利率、日元和套息交易环境",
      "summary": "日本央行最新信息发布与日本利率、日元和套息交易环境相关的新信息，系统将其归入宏观类影响因素，重点观察它对股票、债券、黄金、汇率的传导。正式决策应结合原文链接、后续数据和价格确认。",
      "aiBrief": "AI速读：这条信息主要讲日本利率、日元和套息交易环境，值得跟踪。它可能通过利率预期、美元方向和估值折现率影响股票、债券、黄金、汇率，需要和原文、价格反应以及后续数据一起确认。",
      "watchPoints": [
        "美债收益率和美元是否同步反应",
        "降息或加息概率是否重新定价",
        "股票、债券、黄金、汇率是否出现同向价格确认",
        "同主题是否出现第二个一手信源确认"
      ],
      "tags": [
        "宏观",
        "S级信源",
        "股票、债券、黄金、汇率"
      ],
      "reason": "来自 日本央行最新信息 的高优先级信息，可能影响股票、债券、黄金、汇率。评分综合信源等级、关键词命中、发布时间和影响资产范围。",
      "sourceRank": "S级",
      "absorbed": "部分消化",
      "shortTerm": "短期观察该信息是否在股票、债券、黄金、汇率价格中形成确认。",
      "midTerm": "中期结合后续数据和资金流，判断宏观主线是否延续。",
      "longTerm": "长期意义取决于它是否改变利率、盈利、通胀或风险溢价的基准假设。",
      "decision": "仅作为研究和风控输入，不作为单独交易信号；等待价格、数据和信源交叉确认。"
    },
    {
      "id": "wsj_markets-u-s-treasury-yields-fall-but-direction-for-long-end--c0149fa6",
      "date": "1月27日",
      "time": "10:02",
      "sourceId": "wsj_markets",
      "source": "华尔街日报市场新闻",
      "sourceUrl": "https://www.wsj.com/articles/jgbs-consolidate-supported-by-u-s-treasurys-gains-7edccc7d?mod=rss_markets_main",
      "sourceBrief": "高可信市场媒体，适合捕捉美股、债券、商品和投资者叙事变化。",
      "originalTitle": "U.S. Treasury Yields Fall But Direction for Long-End Yields Still Seen Upward",
      "originalSummary": "The 10-year U.S. Treasury yield fell and ING said the the long end of the Treasury curve will continue trading at higher yields even as Trump hasn’t delivered anything to shock markets so far.",
      "avatar": "W",
      "score": 72,
      "category": "bond",
      "horizon": "mid",
      "asset": "bond equity fx gold",
      "title": "华尔街日报市场新闻观察：财政融资和美债供给",
      "summary": "华尔街日报市场新闻报道了与财政融资和美债供给相关的市场线索，系统将其归入债券类影响因素。它更适合帮助理解市场叙事和资金情绪，仍需用一手数据和价格反应验证。",
      "aiBrief": "AI速读：这是一条媒体解释源，主要讲财政融资和美债供给，值得跟踪。它有助于理解市场正在交易什么叙事，但不能替代官方数据；需要观察股票、债券、黄金、汇率是否给出价格确认。",
      "watchPoints": [
        "长端收益率是否突破近期区间",
        "财政融资或拍卖需求是否继续恶化",
        "股票、债券、黄金、汇率是否出现同向价格确认",
        "同主题是否出现第二个一手信源确认"
      ],
      "tags": [
        "债券",
        "媒体解释源",
        "股票、债券、黄金、汇率"
      ],
      "reason": "来自 华尔街日报市场新闻 的高优先级信息，可能影响股票、债券、黄金、汇率。评分综合信源等级、关键词命中、发布时间和影响资产范围。",
      "sourceRank": "A级",
      "absorbed": "部分消化",
      "shortTerm": "短期观察该信息是否在股票、债券、黄金、汇率价格中形成确认。",
      "midTerm": "中期结合后续数据和资金流，判断债券主线是否延续。",
      "longTerm": "长期意义取决于它是否改变利率、盈利、通胀或风险溢价的基准假设。",
      "decision": "仅作为研究和风控输入，不作为单独交易信号；等待价格、数据和信源交叉确认。"
    },
    {
      "id": "yahoo_finance-stocks-slip-before-the-open-as-oil-rises-on-u-s-iran-01e7340f",
      "date": "5月21日",
      "time": "10:36",
      "sourceId": "yahoo_finance",
      "source": "Yahoo Finance",
      "sourceUrl": "https://finance.yahoo.com/news/stocks-slip-open-oil-rises-103626772.html",
      "sourceBrief": "覆盖面广的财经聚合源，适合补充公司、行业和市场情绪线索。",
      "originalTitle": "Stocks Slip Before the Open as Oil Rises on U.S.-Iran Peace Deal Uncertainty, PMI Data in Focus",
      "originalSummary": "",
      "avatar": "Y",
      "score": 66,
      "category": "commodity",
      "horizon": "short",
      "asset": "commodity equity bond",
      "title": "Yahoo Finance观察：能源供需和通胀传导",
      "summary": "Yahoo Finance报道了与能源供需和通胀传导相关的市场线索，系统将其归入商品类影响因素。它更适合帮助理解市场叙事和资金情绪，仍需用一手数据和价格反应验证。",
      "aiBrief": "AI速读：这是一条媒体解释源，主要讲能源供需和通胀传导，先作为线索观察。它有助于理解市场正在交易什么叙事，但不能替代官方数据；需要观察股票、债券、商品是否给出价格确认。",
      "watchPoints": [
        "库存、供给和现货价格是否同向变化",
        "通胀预期是否被重新抬升",
        "股票、债券、商品是否出现同向价格确认",
        "同主题是否出现第二个一手信源确认"
      ],
      "tags": [
        "商品",
        "媒体解释源",
        "股票、债券、商品"
      ],
      "reason": "来自 Yahoo Finance 的高优先级信息，可能影响股票、债券、商品。评分综合信源等级、关键词命中、发布时间和影响资产范围。",
      "sourceRank": "B级",
      "absorbed": "部分消化",
      "shortTerm": "短期观察该信息是否在股票、债券、商品价格中形成确认。",
      "midTerm": "中期结合后续数据和资金流，判断商品主线是否延续。",
      "longTerm": "长期意义取决于它是否改变利率、盈利、通胀或风险溢价的基准假设。",
      "decision": "仅作为研究和风控输入，不作为单独交易信号；等待价格、数据和信源交叉确认。"
    },
    {
      "id": "marketwatch_pulse-u-s-stock-futures-and-bond-yields-drop-on-reports-pu-c35b62cd",
      "date": "11月19日",
      "time": "08:55",
      "sourceId": "marketwatch_pulse",
      "source": "MarketWatch 快讯",
      "sourceUrl": "https://www.marketwatch.com/story/u-s-stock-futures-and-bond-yields-drop-on-reports-putin-has-updated-nuclear-doctrine-4b9792c4?mod=mw_rss_marketpulse",
      "sourceBrief": "快讯型市场源，适合捕捉经济数据、央行定价和盘中异动。",
      "originalTitle": "U.S. stock futures and bond yields drop on reports Putin has updated nuclear doctrine",
      "originalSummary": "",
      "avatar": "P",
      "score": 63,
      "category": "bond",
      "horizon": "mid",
      "asset": "bond equity fx gold",
      "title": "MarketWatch 快讯观察：利率、债务和期限溢价",
      "summary": "MarketWatch 快讯报道了与利率、债务和期限溢价相关的市场线索，系统将其归入债券类影响因素。它更适合帮助理解市场叙事和资金情绪，仍需用一手数据和价格反应验证。",
      "aiBrief": "AI速读：这是一条媒体解释源，主要讲利率、债务和期限溢价，先作为线索观察。它有助于理解市场正在交易什么叙事，但不能替代官方数据；需要观察股票、债券、黄金、汇率是否给出价格确认。",
      "watchPoints": [
        "长端收益率是否突破近期区间",
        "财政融资或拍卖需求是否继续恶化",
        "股票、债券、黄金、汇率是否出现同向价格确认",
        "同主题是否出现第二个一手信源确认"
      ],
      "tags": [
        "债券",
        "媒体解释源",
        "股票、债券、黄金、汇率"
      ],
      "reason": "来自 MarketWatch 快讯 的高优先级信息，可能影响股票、债券、黄金、汇率。评分综合信源等级、关键词命中、发布时间和影响资产范围。",
      "sourceRank": "A级",
      "absorbed": "部分消化",
      "shortTerm": "短期观察该信息是否在股票、债券、黄金、汇率价格中形成确认。",
      "midTerm": "中期结合后续数据和资金流，判断债券主线是否延续。",
      "longTerm": "长期意义取决于它是否改变利率、盈利、通胀或风险溢价的基准假设。",
      "decision": "仅作为研究和风控输入，不作为单独交易信号；等待价格、数据和信源交叉确认。"
    },
    {
      "id": "bls_macro-4-3-2026-4-7eb4a151",
      "date": "5月22日",
      "time": "20:06",
      "sourceId": "bls_macro",
      "source": "美国劳工统计局公开数据 API",
      "sourceUrl": "https://api.bls.gov/publicAPI/v2/timeseries/data/",
      "sourceBrief": "通胀、就业和工资数据的官方来源，是利率路径和资产估值的重要输入。",
      "originalTitle": "美国失业率最新读数：4.3 %（2026年4月）",
      "originalSummary": "美国劳工统计局官方序列 LNS14000000 在 2026年4月 的读数为 4.3 %；较上一期变化 +0.00。这是判断利率、股票、债券、黄金和汇率的重要就业输入。",
      "avatar": "B",
      "score": 98,
      "category": "macro",
      "horizon": "short",
      "asset": "equity bond gold fx",
      "title": "美国失业率最新读数：4.3 %（2026年4月）",
      "summary": "美国劳工统计局官方序列 LNS14000000 在 2026年4月 的读数为 4.3 %；较上一期变化 +0.00。这是判断利率、股票、债券、黄金和汇率的重要就业输入。",
      "aiBrief": "AI速读：这条信息主要讲就业，优先级很高。它可能通过利率预期、美元方向和估值折现率影响股票、债券、黄金、汇率，需要和原文、价格反应以及后续数据一起确认。",
      "watchPoints": [
        "美债收益率和美元是否同步反应",
        "降息或加息概率是否重新定价",
        "股票、债券、黄金、汇率是否出现同向价格确认",
        "同主题是否出现第二个一手信源确认"
      ],
      "tags": [
        "宏观",
        "S级信源",
        "股票、债券、黄金、汇率"
      ],
      "reason": "来自 美国劳工统计局公开数据 API 的高优先级信息，可能影响股票、债券、黄金、汇率。评分综合信源等级、关键词命中、发布时间和影响资产范围。",
      "sourceRank": "S级",
      "absorbed": "尚未完全消化",
      "shortTerm": "短期观察该信息是否在股票、债券、黄金、汇率价格中形成确认。",
      "midTerm": "中期结合后续数据和资金流，判断宏观主线是否延续。",
      "longTerm": "长期意义取决于它是否改变利率、盈利、通胀或风险溢价的基准假设。",
      "decision": "仅作为研究和风控输入，不作为单独交易信号；等待价格、数据和信源交叉确认。"
    },
    {
      "id": "bls_macro-158736-2026-4-c0596985",
      "date": "5月22日",
      "time": "20:06",
      "sourceId": "bls_macro",
      "source": "美国劳工统计局公开数据 API",
      "sourceUrl": "https://api.bls.gov/publicAPI/v2/timeseries/data/",
      "sourceBrief": "通胀、就业和工资数据的官方来源，是利率路径和资产估值的重要输入。",
      "originalTitle": "美国非农就业总人数最新读数：158736 千人（2026年4月）",
      "originalSummary": "美国劳工统计局官方序列 CES0000000001 在 2026年4月 的读数为 158736 千人；较上一期变化 +115.00。这是判断利率、股票、债券、黄金和汇率的重要就业输入。",
      "avatar": "B",
      "score": 98,
      "category": "macro",
      "horizon": "short",
      "asset": "equity bond gold fx",
      "title": "美国非农就业总人数最新读数：158736 千人（2026年4月）",
      "summary": "美国劳工统计局官方序列 CES0000000001 在 2026年4月 的读数为 158736 千人；较上一期变化 +115.00。这是判断利率、股票、债券、黄金和汇率的重要就业输入。",
      "aiBrief": "AI速读：这条信息主要讲就业，优先级很高。它可能通过利率预期、美元方向和估值折现率影响股票、债券、黄金、汇率，需要和原文、价格反应以及后续数据一起确认。",
      "watchPoints": [
        "美债收益率和美元是否同步反应",
        "降息或加息概率是否重新定价",
        "股票、债券、黄金、汇率是否出现同向价格确认",
        "同主题是否出现第二个一手信源确认"
      ],
      "tags": [
        "宏观",
        "S级信源",
        "股票、债券、黄金、汇率"
      ],
      "reason": "来自 美国劳工统计局公开数据 API 的高优先级信息，可能影响股票、债券、黄金、汇率。评分综合信源等级、关键词命中、发布时间和影响资产范围。",
      "sourceRank": "S级",
      "absorbed": "尚未完全消化",
      "shortTerm": "短期观察该信息是否在股票、债券、黄金、汇率价格中形成确认。",
      "midTerm": "中期结合后续数据和资金流，判断宏观主线是否延续。",
      "longTerm": "长期意义取决于它是否改变利率、盈利、通胀或风险溢价的基准假设。",
      "decision": "仅作为研究和风控输入，不作为单独交易信号；等待价格、数据和信源交叉确认。"
    },
    {
      "id": "fed_press-federal-reserve-board-requests-public-comment-on-a-p-4c7fcb30",
      "date": "5月20日",
      "time": "20:00",
      "sourceId": "fed_press",
      "source": "美联储新闻稿",
      "sourceUrl": "https://www.federalreserve.gov/newsevents/pressreleases/other20260520a.htm",
      "sourceBrief": "美国货币政策、金融监管和利率预期的一手信源。",
      "originalTitle": "Federal Reserve Board requests public comment on a proposal to establish a \"payment account,\" which legally eligible financial institutions could use for the specific purpose of clearing and settling their payments",
      "originalSummary": "Federal Reserve Board requests public comment on a proposal to establish a \"payment account,\" which legally eligible financial institutions could use for the specific purpose of clearing and settling their payments",
      "avatar": "F",
      "score": 93,
      "category": "macro",
      "horizon": "short",
      "asset": "equity bond gold fx",
      "title": "美联储新闻稿更新：宏观数据和政策预期",
      "summary": "美联储新闻稿发布与宏观数据和政策预期相关的新信息，系统将其归入宏观类影响因素，重点观察它对股票、债券、黄金、汇率的传导。正式决策应结合原文链接、后续数据和价格确认。",
      "aiBrief": "AI速读：这条信息主要讲宏观数据和政策预期，优先级很高。它可能通过利率预期、美元方向和估值折现率影响股票、债券、黄金、汇率，需要和原文、价格反应以及后续数据一起确认。",
      "watchPoints": [
        "美债收益率和美元是否同步反应",
        "降息或加息概率是否重新定价",
        "股票、债券、黄金、汇率是否出现同向价格确认",
        "同主题是否出现第二个一手信源确认"
      ],
      "tags": [
        "宏观",
        "S级信源",
        "股票、债券、黄金、汇率"
      ],
      "reason": "来自 美联储新闻稿 的高优先级信息，可能影响股票、债券、黄金、汇率。评分综合信源等级、关键词命中、发布时间和影响资产范围。",
      "sourceRank": "S级",
      "absorbed": "尚未完全消化",
      "shortTerm": "短期观察该信息是否在股票、债券、黄金、汇率价格中形成确认。",
      "midTerm": "中期结合后续数据和资金流，判断宏观主线是否延续。",
      "longTerm": "长期意义取决于它是否改变利率、盈利、通胀或风险溢价的基准假设。",
      "decision": "仅作为研究和风控输入，不作为单独交易信号；等待价格、数据和信源交叉确认。"
    },
    {
      "id": "ecb_press-results-of-the-march-2026-survey-on-credit-terms-and-e8eec3ba",
      "date": "5月20日",
      "time": "09:00",
      "sourceId": "ecb_press",
      "source": "欧洲央行新闻与讲话",
      "sourceUrl": "https://www.ecb.europa.eu//press/pr/date/2026/html/ecb.pr260520~feb373ad0d.en.html",
      "sourceBrief": "欧元区货币政策、通胀判断和金融稳定的一手信源。",
      "originalTitle": "Results of the March 2026 survey on credit terms and conditions in euro-denominated securities financing and OTC derivatives markets (SESFOD)",
      "originalSummary": "",
      "avatar": "E",
      "score": 91,
      "category": "equity",
      "horizon": "mid",
      "asset": "equity",
      "title": "欧洲央行新闻与讲话更新：资本市场监管和公司风险",
      "summary": "欧洲央行新闻与讲话发布与资本市场监管和公司风险相关的新信息，系统将其归入股票类影响因素，重点观察它对股票的传导。正式决策应结合原文链接、后续数据和价格确认。",
      "aiBrief": "AI速读：这条信息主要讲资本市场监管和公司风险，优先级很高。它可能通过盈利预期、估值风险和资金偏好影响股票，需要和原文、价格反应以及后续数据一起确认。",
      "watchPoints": [
        "相关板块 ETF 和龙头股是否放量反应",
        "盈利预期或监管风险是否扩散",
        "股票是否出现同向价格确认",
        "同主题是否出现第二个一手信源确认"
      ],
      "tags": [
        "股票",
        "S级信源",
        "股票"
      ],
      "reason": "来自 欧洲央行新闻与讲话 的高优先级信息，可能影响股票。评分综合信源等级、关键词命中、发布时间和影响资产范围。",
      "sourceRank": "S级",
      "absorbed": "尚未完全消化",
      "shortTerm": "短期观察该信息是否在股票价格中形成确认。",
      "midTerm": "中期结合后续数据和资金流，判断股票主线是否延续。",
      "longTerm": "长期意义取决于它是否改变利率、盈利、通胀或风险溢价的基准假设。",
      "decision": "仅作为研究和风控输入，不作为单独交易信号；等待价格、数据和信源交叉确认。"
    },
    {
      "id": "treasury_press-treasury-disrupts-sinaloa-cartel-narco-terrorist-fen-15aaf870",
      "date": "5月22日",
      "time": "20:06",
      "sourceId": "treasury_press",
      "source": "美国财政部新闻稿",
      "sourceUrl": "https://home.treasury.gov/news/press-releases/sb0503",
      "sourceBrief": "财政、发债、制裁和跨境资金政策的官方来源，会影响美债、美元和风险偏好。",
      "originalTitle": "Treasury Disrupts Sinaloa Cartel Narco-Terrorist Fentanyl Trafficking Operations",
      "originalSummary": "",
      "avatar": "T",
      "score": 90,
      "category": "bond",
      "horizon": "mid",
      "asset": "bond equity fx gold",
      "title": "美国财政部新闻稿更新：财政融资和美债供给",
      "summary": "美国财政部新闻稿发布与财政融资和美债供给相关的新信息，系统将其归入债券类影响因素，重点观察它对股票、债券、黄金、汇率的传导。正式决策应结合原文链接、后续数据和价格确认。",
      "aiBrief": "AI速读：这条信息主要讲财政融资和美债供给，优先级很高。它可能通过收益率曲线、期限溢价和美元流动性影响股票、债券、黄金、汇率，需要和原文、价格反应以及后续数据一起确认。",
      "watchPoints": [
        "长端收益率是否突破近期区间",
        "财政融资或拍卖需求是否继续恶化",
        "股票、债券、黄金、汇率是否出现同向价格确认",
        "同主题是否出现第二个一手信源确认"
      ],
      "tags": [
        "债券",
        "S级信源",
        "股票、债券、黄金、汇率"
      ],
      "reason": "来自 美国财政部新闻稿 的高优先级信息，可能影响股票、债券、黄金、汇率。评分综合信源等级、关键词命中、发布时间和影响资产范围。",
      "sourceRank": "S级",
      "absorbed": "尚未完全消化",
      "shortTerm": "短期观察该信息是否在股票、债券、黄金、汇率价格中形成确认。",
      "midTerm": "中期结合后续数据和资金流，判断债券主线是否延续。",
      "longTerm": "长期意义取决于它是否改变利率、盈利、通胀或风险溢价的基准假设。",
      "decision": "仅作为研究和风控输入，不作为单独交易信号；等待价格、数据和信源交叉确认。"
    },
    {
      "id": "bloomberg_markets-gold-drops-as-fed-s-waller-says-next-move-likely-to--bd5e16ee",
      "date": "5月21日",
      "time": "22:34",
      "sourceId": "bloomberg_markets",
      "source": "Bloomberg Markets",
      "sourceUrl": "https://www.bloomberg.com/news/articles/2026-05-21/gold-steady-as-us-iran-signals-keep-rate-hike-bets-simmering",
      "sourceBrief": "全球市场新闻源，适合捕捉宏观、地缘、央行和资产价格叙事。",
      "originalTitle": "Gold Drops as Fed’s Waller Says Next Move Likely To Be Rate Hike",
      "originalSummary": "Gold declined as traders ramped up bets on Federal Reserve monetary tightening after Governor Christopher Waller warned the Iran war’s energy shock could fuel inflation.",
      "avatar": "L",
      "score": 89,
      "category": "macro",
      "horizon": "short",
      "asset": "equity bond gold fx",
      "title": "Bloomberg Markets观察：通胀压力和实际利率",
      "summary": "Bloomberg Markets报道了与通胀压力和实际利率相关的市场线索，系统将其归入宏观类影响因素。它更适合帮助理解市场叙事和资金情绪，仍需用一手数据和价格反应验证。",
      "aiBrief": "AI速读：这是一条媒体解释源，主要讲通胀压力和实际利率，优先级很高。它有助于理解市场正在交易什么叙事，但不能替代官方数据；需要观察股票、债券、黄金、汇率是否给出价格确认。",
      "watchPoints": [
        "美债收益率和美元是否同步反应",
        "降息或加息概率是否重新定价",
        "股票、债券、黄金、汇率是否出现同向价格确认",
        "同主题是否出现第二个一手信源确认"
      ],
      "tags": [
        "宏观",
        "媒体解释源",
        "股票、债券、黄金、汇率"
      ],
      "reason": "来自 Bloomberg Markets 的高优先级信息，可能影响股票、债券、黄金、汇率。评分综合信源等级、关键词命中、发布时间和影响资产范围。",
      "sourceRank": "A级",
      "absorbed": "尚未完全消化",
      "shortTerm": "短期观察该信息是否在股票、债券、黄金、汇率价格中形成确认。",
      "midTerm": "中期结合后续数据和资金流，判断宏观主线是否延续。",
      "longTerm": "长期意义取决于它是否改变利率、盈利、通胀或风险溢价的基准假设。",
      "decision": "仅作为研究和风控输入，不作为单独交易信号；等待价格、数据和信源交叉确认。"
    },
    {
      "id": "ecb_press-frank-elderson-a-central-banker-s-perspective-on-cli-72f7e53c",
      "date": "5月21日",
      "time": "15:30",
      "sourceId": "ecb_press",
      "source": "欧洲央行新闻与讲话",
      "sourceUrl": "https://www.ecb.europa.eu//press/key/date/2026/html/ecb.sp260521~ccae6782e3.en.pdf",
      "sourceBrief": "欧元区货币政策、通胀判断和金融稳定的一手信源。",
      "originalTitle": "Frank Elderson: A central banker’s perspective on climate change and nature degradation",
      "originalSummary": "",
      "avatar": "E",
      "score": 89,
      "category": "macro",
      "horizon": "short",
      "asset": "equity bond gold fx",
      "title": "欧洲央行新闻与讲话更新：欧元区政策、通胀和金融稳定",
      "summary": "欧洲央行新闻与讲话发布与欧元区政策、通胀和金融稳定相关的新信息，系统将其归入宏观类影响因素，重点观察它对股票、债券、黄金、汇率的传导。正式决策应结合原文链接、后续数据和价格确认。",
      "aiBrief": "AI速读：这条信息主要讲欧元区政策、通胀和金融稳定，优先级很高。它可能通过利率预期、美元方向和估值折现率影响股票、债券、黄金、汇率，需要和原文、价格反应以及后续数据一起确认。",
      "watchPoints": [
        "美债收益率和美元是否同步反应",
        "降息或加息概率是否重新定价",
        "股票、债券、黄金、汇率是否出现同向价格确认",
        "同主题是否出现第二个一手信源确认"
      ],
      "tags": [
        "宏观",
        "S级信源",
        "股票、债券、黄金、汇率"
      ],
      "reason": "来自 欧洲央行新闻与讲话 的高优先级信息，可能影响股票、债券、黄金、汇率。评分综合信源等级、关键词命中、发布时间和影响资产范围。",
      "sourceRank": "S级",
      "absorbed": "尚未完全消化",
      "shortTerm": "短期观察该信息是否在股票、债券、黄金、汇率价格中形成确认。",
      "midTerm": "中期结合后续数据和资金流，判断宏观主线是否延续。",
      "longTerm": "长期意义取决于它是否改变利率、盈利、通胀或风险溢价的基准假设。",
      "decision": "仅作为研究和风控输入，不作为单独交易信号；等待价格、数据和信源交叉确认。"
    },
    {
      "id": "eia_energy-the-united-states-set-record-energy-production-in-20-99a0a6a5",
      "date": "5月11日",
      "time": "14:00",
      "sourceId": "eia_energy",
      "source": "美国能源信息署能源日报",
      "sourceUrl": "https://www.eia.gov/todayinenergy/detail.php?id=67684",
      "sourceBrief": "能源供需、库存和价格压力的官方线索，主要影响原油、通胀和能源股。",
      "originalTitle": "The United States set record energy production in 2025, again",
      "originalSummary": "Total energy production in the United States increased to a new record of 107 quadrillion British thermal units (quads) in 2025, a 3.4% increase from the previous record set in 2024, according to new data in our Monthly Energy Review. Total production was driven by record-high production in natural gas, crude oil, natural gas plant liquids (NGPLs), and renewables. This was the fourth consecutive year in which the United States set a record for total energy production.",
      "avatar": "E",
      "score": 87,
      "category": "commodity",
      "horizon": "short",
      "asset": "commodity equity bond",
      "title": "美国能源信息署能源日报更新：能源供需和通胀传导",
      "summary": "美国能源信息署能源日报发布与能源供需和通胀传导相关的新信息，系统将其归入商品类影响因素，重点观察它对股票、债券、商品的传导。正式决策应结合原文链接、后续数据和价格确认。",
      "aiBrief": "AI速读：这条信息主要讲能源供需和通胀传导，优先级很高。它可能通过通胀预期、成本压力和周期资产表现影响股票、债券、商品，需要和原文、价格反应以及后续数据一起确认。",
      "watchPoints": [
        "库存、供给和现货价格是否同向变化",
        "通胀预期是否被重新抬升",
        "股票、债券、商品是否出现同向价格确认",
        "同主题是否出现第二个一手信源确认"
      ],
      "tags": [
        "商品",
        "S级信源",
        "股票、债券、商品"
      ],
      "reason": "来自 美国能源信息署能源日报 的高优先级信息，可能影响股票、债券、商品。评分综合信源等级、关键词命中、发布时间和影响资产范围。",
      "sourceRank": "S级",
      "absorbed": "尚未完全消化",
      "shortTerm": "短期观察该信息是否在股票、债券、商品价格中形成确认。",
      "midTerm": "中期结合后续数据和资金流，判断商品主线是否延续。",
      "longTerm": "长期意义取决于它是否改变利率、盈利、通胀或风险溢价的基准假设。",
      "decision": "仅作为研究和风控输入，不作为单独交易信号；等待价格、数据和信源交叉确认。"
    },
    {
      "id": "eia_energy-doe-has-released-17-5-million-barrels-from-the-strat-f8950cb2",
      "date": "4月30日",
      "time": "14:00",
      "sourceId": "eia_energy",
      "source": "美国能源信息署能源日报",
      "sourceUrl": "https://www.eia.gov/todayinenergy/detail.php?id=67625",
      "sourceBrief": "能源供需、库存和价格压力的官方线索，主要影响原油、通胀和能源股。",
      "originalTitle": "DOE has released 17.5 million barrels from the Strategic Petroleum Reserve since March",
      "originalSummary": "Between the week ending March 20 and the week ending April 24, the U.S. Department of Energy (DOE) released a total of 17.5 million barrels of crude oil from the U.S. Strategic Petroleum Reserve (SPR), according to data in our Weekly Petroleum Status Report. DOE released 7.1 million barrels in the week ending April 24, the most released since the week ending October 7, 2022. SPR stocks are currently 397.9 million barrels.",
      "avatar": "E",
      "score": 87,
      "category": "commodity",
      "horizon": "short",
      "asset": "commodity equity bond",
      "title": "美国能源信息署能源日报更新：能源供需和通胀传导",
      "summary": "美国能源信息署能源日报发布与能源供需和通胀传导相关的新信息，系统将其归入商品类影响因素，重点观察它对股票、债券、商品的传导。正式决策应结合原文链接、后续数据和价格确认。",
      "aiBrief": "AI速读：这条信息主要讲能源供需和通胀传导，优先级很高。它可能通过通胀预期、成本压力和周期资产表现影响股票、债券、商品，需要和原文、价格反应以及后续数据一起确认。",
      "watchPoints": [
        "库存、供给和现货价格是否同向变化",
        "通胀预期是否被重新抬升",
        "股票、债券、商品是否出现同向价格确认",
        "同主题是否出现第二个一手信源确认"
      ],
      "tags": [
        "商品",
        "S级信源",
        "股票、债券、商品"
      ],
      "reason": "来自 美国能源信息署能源日报 的高优先级信息，可能影响股票、债券、商品。评分综合信源等级、关键词命中、发布时间和影响资产范围。",
      "sourceRank": "S级",
      "absorbed": "尚未完全消化",
      "shortTerm": "短期观察该信息是否在股票、债券、商品价格中形成确认。",
      "midTerm": "中期结合后续数据和资金流，判断商品主线是否延续。",
      "longTerm": "长期意义取决于它是否改变利率、盈利、通胀或风险溢价的基准假设。",
      "decision": "仅作为研究和风控输入，不作为单独交易信号；等待价格、数据和信源交叉确认。"
    },
    {
      "id": "bloomberg_markets-retail-s-k-shaped-economy-ef3e3c13",
      "date": "5月22日",
      "time": "16:10",
      "sourceId": "bloomberg_markets",
      "source": "Bloomberg Markets",
      "sourceUrl": "https://www.bloomberg.com/news/videos/2026-05-22/retail-s-k-shaped-economy-video",
      "sourceBrief": "全球市场新闻源，适合捕捉宏观、地缘、央行和资产价格叙事。",
      "originalTitle": "Retail’s K-Shaped Economy",
      "originalSummary": "Inflation is exposing a major divide in the US economy according to Citi Retailing and Hardlines Analyst Steven Zaccone, He joins Bloomberg Open Interest to explain why wealthy consumers keep spending while lower-income shoppers struggle with rising gas and living costs. From Walmart and BJ’s to Williams-Sonoma and AutoZone, we look at the retail winners and losers in today’s “K-shaped” economy. (Source: Bloomberg)",
      "avatar": "L",
      "score": 85,
      "category": "macro",
      "horizon": "short",
      "asset": "equity bond gold fx",
      "title": "Bloomberg Markets观察：通胀压力和实际利率",
      "summary": "Bloomberg Markets报道了与通胀压力和实际利率相关的市场线索，系统将其归入宏观类影响因素。它更适合帮助理解市场叙事和资金情绪，仍需用一手数据和价格反应验证。",
      "aiBrief": "AI速读：这是一条媒体解释源，主要讲通胀压力和实际利率，优先级很高。它有助于理解市场正在交易什么叙事，但不能替代官方数据；需要观察股票、债券、黄金、汇率是否给出价格确认。",
      "watchPoints": [
        "美债收益率和美元是否同步反应",
        "降息或加息概率是否重新定价",
        "股票、债券、黄金、汇率是否出现同向价格确认",
        "同主题是否出现第二个一手信源确认"
      ],
      "tags": [
        "宏观",
        "媒体解释源",
        "股票、债券、黄金、汇率"
      ],
      "reason": "来自 Bloomberg Markets 的高优先级信息，可能影响股票、债券、黄金、汇率。评分综合信源等级、关键词命中、发布时间和影响资产范围。",
      "sourceRank": "A级",
      "absorbed": "尚未完全消化",
      "shortTerm": "短期观察该信息是否在股票、债券、黄金、汇率价格中形成确认。",
      "midTerm": "中期结合后续数据和资金流，判断宏观主线是否延续。",
      "longTerm": "长期意义取决于它是否改变利率、盈利、通胀或风险溢价的基准假设。",
      "decision": "仅作为研究和风控输入，不作为单独交易信号；等待价格、数据和信源交叉确认。"
    },
    {
      "id": "fed_press-federal-reserve-board-releases-results-from-two-surv-3ceee7ef",
      "date": "5月14日",
      "time": "14:00",
      "sourceId": "fed_press",
      "source": "美联储新闻稿",
      "sourceUrl": "https://www.federalreserve.gov/newsevents/pressreleases/other20260514a.htm",
      "sourceBrief": "美国货币政策、金融监管和利率预期的一手信源。",
      "originalTitle": "Federal Reserve Board releases results from two surveys of senior financial officers at banks about their views on discount window operating days and their strategies and practices for managing reserve balances",
      "originalSummary": "Federal Reserve Board releases results from two surveys of senior financial officers at banks about their views on discount window operating days and their strategies and practices for managing reserve balances",
      "avatar": "F",
      "score": 85,
      "category": "macro",
      "horizon": "short",
      "asset": "equity bond gold fx",
      "title": "美联储新闻稿更新：全球流动性和金融稳定",
      "summary": "美联储新闻稿发布与全球流动性和金融稳定相关的新信息，系统将其归入宏观类影响因素，重点观察它对股票、债券、黄金、汇率的传导。正式决策应结合原文链接、后续数据和价格确认。",
      "aiBrief": "AI速读：这条信息主要讲全球流动性和金融稳定，优先级很高。它可能通过利率预期、美元方向和估值折现率影响股票、债券、黄金、汇率，需要和原文、价格反应以及后续数据一起确认。",
      "watchPoints": [
        "美债收益率和美元是否同步反应",
        "降息或加息概率是否重新定价",
        "股票、债券、黄金、汇率是否出现同向价格确认",
        "同主题是否出现第二个一手信源确认"
      ],
      "tags": [
        "宏观",
        "S级信源",
        "股票、债券、黄金、汇率"
      ],
      "reason": "来自 美联储新闻稿 的高优先级信息，可能影响股票、债券、黄金、汇率。评分综合信源等级、关键词命中、发布时间和影响资产范围。",
      "sourceRank": "S级",
      "absorbed": "尚未完全消化",
      "shortTerm": "短期观察该信息是否在股票、债券、黄金、汇率价格中形成确认。",
      "midTerm": "中期结合后续数据和资金流，判断宏观主线是否延续。",
      "longTerm": "长期意义取决于它是否改变利率、盈利、通胀或风险溢价的基准假设。",
      "decision": "仅作为研究和风控输入，不作为单独交易信号；等待价格、数据和信源交叉确认。"
    },
    {
      "id": "fed_press-federal-reserve-board-issues-economic-well-being-of--de5aa138",
      "date": "5月13日",
      "time": "15:30",
      "sourceId": "fed_press",
      "source": "美联储新闻稿",
      "sourceUrl": "https://www.federalreserve.gov/newsevents/pressreleases/other20260513a.htm",
      "sourceBrief": "美国货币政策、金融监管和利率预期的一手信源。",
      "originalTitle": "Federal Reserve Board issues Economic Well-Being of U.S. Households in 2025 report",
      "originalSummary": "Federal Reserve Board issues Economic Well-Being of U.S. Households in 2025 report",
      "avatar": "F",
      "score": 85,
      "category": "macro",
      "horizon": "short",
      "asset": "equity bond gold fx",
      "title": "美联储新闻稿更新：宏观数据和政策预期",
      "summary": "美联储新闻稿发布与宏观数据和政策预期相关的新信息，系统将其归入宏观类影响因素，重点观察它对股票、债券、黄金、汇率的传导。正式决策应结合原文链接、后续数据和价格确认。",
      "aiBrief": "AI速读：这条信息主要讲宏观数据和政策预期，优先级很高。它可能通过利率预期、美元方向和估值折现率影响股票、债券、黄金、汇率，需要和原文、价格反应以及后续数据一起确认。",
      "watchPoints": [
        "美债收益率和美元是否同步反应",
        "降息或加息概率是否重新定价",
        "股票、债券、黄金、汇率是否出现同向价格确认",
        "同主题是否出现第二个一手信源确认"
      ],
      "tags": [
        "宏观",
        "S级信源",
        "股票、债券、黄金、汇率"
      ],
      "reason": "来自 美联储新闻稿 的高优先级信息，可能影响股票、债券、黄金、汇率。评分综合信源等级、关键词命中、发布时间和影响资产范围。",
      "sourceRank": "S级",
      "absorbed": "尚未完全消化",
      "shortTerm": "短期观察该信息是否在股票、债券、黄金、汇率价格中形成确认。",
      "midTerm": "中期结合后续数据和资金流，判断宏观主线是否延续。",
      "longTerm": "长期意义取决于它是否改变利率、盈利、通胀或风险溢价的基准假设。",
      "decision": "仅作为研究和风控输入，不作为单独交易信号；等待价格、数据和信源交叉确认。"
    },
    {
      "id": "eia_energy-alaska-proved-reserves-increased-in-2024-while-natio-f0b111dc",
      "date": "4月29日",
      "time": "14:00",
      "sourceId": "eia_energy",
      "source": "美国能源信息署能源日报",
      "sourceUrl": "https://www.eia.gov/todayinenergy/detail.php?id=67624",
      "sourceBrief": "能源供需、库存和价格压力的官方线索，主要影响原油、通胀和能源股。",
      "originalTitle": "Alaska proved reserves increased in 2024, while nationwide proved reserves fell",
      "originalSummary": "Oil and gas producers operating in Alaska reported increases in proved reserves in 2024 at a time when low prices triggered a decrease in nationwide proved reserves, according to our recently released U.S. Crude Oil and Natural Gas Proved Reserves, Year-End 2024 report. Alaska's crude oil and lease condensate proved reserves increased 5%, and natural gas proved reserves increased nearly 7% in 2024.",
      "avatar": "E",
      "score": 85,
      "category": "commodity",
      "horizon": "short",
      "asset": "commodity equity bond",
      "title": "美国能源信息署能源日报更新：通胀压力和实际利率",
      "summary": "美国能源信息署能源日报发布与通胀压力和实际利率相关的新信息，系统将其归入商品类影响因素，重点观察它对股票、债券、商品的传导。正式决策应结合原文链接、后续数据和价格确认。",
      "aiBrief": "AI速读：这条信息主要讲通胀压力和实际利率，优先级很高。它可能通过通胀预期、成本压力和周期资产表现影响股票、债券、商品，需要和原文、价格反应以及后续数据一起确认。",
      "watchPoints": [
        "库存、供给和现货价格是否同向变化",
        "通胀预期是否被重新抬升",
        "股票、债券、商品是否出现同向价格确认",
        "同主题是否出现第二个一手信源确认"
      ],
      "tags": [
        "商品",
        "S级信源",
        "股票、债券、商品"
      ],
      "reason": "来自 美国能源信息署能源日报 的高优先级信息，可能影响股票、债券、商品。评分综合信源等级、关键词命中、发布时间和影响资产范围。",
      "sourceRank": "S级",
      "absorbed": "尚未完全消化",
      "shortTerm": "短期观察该信息是否在股票、债券、商品价格中形成确认。",
      "midTerm": "中期结合后续数据和资金流，判断商品主线是否延续。",
      "longTerm": "长期意义取决于它是否改变利率、盈利、通胀或风险溢价的基准假设。",
      "decision": "仅作为研究和风控输入，不作为单独交易信号；等待价格、数据和信源交叉确认。"
    },
    {
      "id": "bloomberg_markets-muni-bond-sales-surge-in-2026-d829eaa5",
      "date": "5月22日",
      "time": "19:43",
      "sourceId": "bloomberg_markets",
      "source": "Bloomberg Markets",
      "sourceUrl": "https://www.bloomberg.com/news/videos/2026-05-22/muni-bond-sales-surge-in-2026-video",
      "sourceBrief": "全球市场新闻源，适合捕捉宏观、地缘、央行和资产价格叙事。",
      "originalTitle": "Muni Bond Sales Surge in 2026",
      "originalSummary": "Bloomberg's Aashah Shah joins Scarlet Fu on \"Bloomberg Real Yield.\" May has been a strong month for muni bond issuance, with about $35 billion of sales so far this year. This month has seen the most debt for a similar period in May since at least 2015, Bloomberg data show. (Source: Bloomberg)",
      "avatar": "L",
      "score": 83,
      "category": "bond",
      "horizon": "mid",
      "asset": "bond equity fx gold",
      "title": "Bloomberg Markets观察：消费需求和企业收入",
      "summary": "Bloomberg Markets报道了与消费需求和企业收入相关的市场线索，系统将其归入债券类影响因素。它更适合帮助理解市场叙事和资金情绪，仍需用一手数据和价格反应验证。",
      "aiBrief": "AI速读：这是一条媒体解释源，主要讲消费需求和企业收入，值得跟踪。它有助于理解市场正在交易什么叙事，但不能替代官方数据；需要观察股票、债券、黄金、汇率是否给出价格确认。",
      "watchPoints": [
        "长端收益率是否突破近期区间",
        "财政融资或拍卖需求是否继续恶化",
        "股票、债券、黄金、汇率是否出现同向价格确认",
        "同主题是否出现第二个一手信源确认"
      ],
      "tags": [
        "债券",
        "媒体解释源",
        "股票、债券、黄金、汇率"
      ],
      "reason": "来自 Bloomberg Markets 的高优先级信息，可能影响股票、债券、黄金、汇率。评分综合信源等级、关键词命中、发布时间和影响资产范围。",
      "sourceRank": "A级",
      "absorbed": "尚未完全消化",
      "shortTerm": "短期观察该信息是否在股票、债券、黄金、汇率价格中形成确认。",
      "midTerm": "中期结合后续数据和资金流，判断债券主线是否延续。",
      "longTerm": "长期意义取决于它是否改变利率、盈利、通胀或风险溢价的基准假设。",
      "decision": "仅作为研究和风控输入，不作为单独交易信号；等待价格、数据和信源交叉确认。"
    },
    {
      "id": "ecb_press-european-central-bank-and-reserve-bank-of-india-sign-0ff79b81",
      "date": "5月10日",
      "time": "13:00",
      "sourceId": "ecb_press",
      "source": "欧洲央行新闻与讲话",
      "sourceUrl": "https://www.ecb.europa.eu//press/pr/date/2026/html/ecb.pr260510~e8a674e2fb.en.html",
      "sourceBrief": "欧元区货币政策、通胀判断和金融稳定的一手信源。",
      "originalTitle": "European Central Bank and Reserve Bank of India sign Memorandum of Understanding on cooperation",
      "originalSummary": "",
      "avatar": "E",
      "score": 83,
      "category": "gold",
      "horizon": "mid",
      "asset": "gold fx bond",
      "title": "欧洲央行新闻与讲话更新：欧元区政策、通胀和金融稳定",
      "summary": "欧洲央行新闻与讲话发布与欧元区政策、通胀和金融稳定相关的新信息，系统将其归入黄金类影响因素，重点观察它对债券、黄金、汇率的传导。正式决策应结合原文链接、后续数据和价格确认。",
      "aiBrief": "AI速读：这条信息主要讲欧元区政策、通胀和金融稳定，值得跟踪。它可能通过实际利率、美元和央行储备偏好影响债券、黄金、汇率，需要和原文、价格反应以及后续数据一起确认。",
      "watchPoints": [
        "实际利率和美元是否压制金价",
        "黄金 ETF 或央行购金线索是否延续",
        "债券、黄金、汇率是否出现同向价格确认",
        "同主题是否出现第二个一手信源确认"
      ],
      "tags": [
        "黄金",
        "S级信源",
        "债券、黄金、汇率"
      ],
      "reason": "来自 欧洲央行新闻与讲话 的高优先级信息，可能影响债券、黄金、汇率。评分综合信源等级、关键词命中、发布时间和影响资产范围。",
      "sourceRank": "S级",
      "absorbed": "尚未完全消化",
      "shortTerm": "短期观察该信息是否在债券、黄金、汇率价格中形成确认。",
      "midTerm": "中期结合后续数据和资金流，判断黄金主线是否延续。",
      "longTerm": "长期意义取决于它是否改变利率、盈利、通胀或风险溢价的基准假设。",
      "decision": "仅作为研究和风控输入，不作为单独交易信号；等待价格、数据和信源交叉确认。"
    },
    {
      "id": "sec_press-sec-and-nfa-announce-memorandum-of-understanding-to--e7280b91",
      "date": "5月21日",
      "time": "12:51",
      "sourceId": "sec_press",
      "source": "美国 SEC 新闻稿",
      "sourceUrl": "https://www.sec.gov/newsroom/press-releases/2026-47",
      "sourceBrief": "资本市场监管、执法和披露风险的一手信源。",
      "originalTitle": "SEC and NFA Announce Memorandum of Understanding to Further Harmonize Regulatory Coordination",
      "originalSummary": "The Securities and Exchange Commission (SEC) and National Futures Association (NFA) today announced that they have entered into a Memorandum of Understanding (MOU) to enhance their cooperation, coordination, and information sharing in areas of common…",
      "avatar": "S",
      "score": 81,
      "category": "equity",
      "horizon": "mid",
      "asset": "equity",
      "title": "美国 SEC 新闻稿更新：资本市场监管和公司风险",
      "summary": "美国 SEC 新闻稿发布与资本市场监管和公司风险相关的新信息，系统将其归入股票类影响因素，重点观察它对股票的传导。正式决策应结合原文链接、后续数据和价格确认。",
      "aiBrief": "AI速读：这条信息主要讲资本市场监管和公司风险，值得跟踪。它可能通过盈利预期、估值风险和资金偏好影响股票，需要和原文、价格反应以及后续数据一起确认。",
      "watchPoints": [
        "相关板块 ETF 和龙头股是否放量反应",
        "盈利预期或监管风险是否扩散",
        "股票是否出现同向价格确认",
        "同主题是否出现第二个一手信源确认"
      ],
      "tags": [
        "股票",
        "S级信源",
        "股票"
      ],
      "reason": "来自 美国 SEC 新闻稿 的高优先级信息，可能影响股票。评分综合信源等级、关键词命中、发布时间和影响资产范围。",
      "sourceRank": "S级",
      "absorbed": "尚未完全消化",
      "shortTerm": "短期观察该信息是否在股票价格中形成确认。",
      "midTerm": "中期结合后续数据和资金流，判断股票主线是否延续。",
      "longTerm": "长期意义取决于它是否改变利率、盈利、通胀或风险溢价的基准假设。",
      "decision": "仅作为研究和风控输入，不作为单独交易信号；等待价格、数据和信源交叉确认。"
    },
    {
      "id": "sec_press-sec-proposes-transformative-reforms-to-help-public-c-c5a9996e",
      "date": "5月19日",
      "time": "14:55",
      "sourceId": "sec_press",
      "source": "美国 SEC 新闻稿",
      "sourceUrl": "https://www.sec.gov/newsroom/press-releases/2026-46-sec-proposes-transformative-reforms-help-public-companies-conduct-registered-offerings-simplify",
      "sourceBrief": "资本市场监管、执法和披露风险的一手信源。",
      "originalTitle": "SEC Proposes Transformative Reforms to Help Public Companies Conduct Registered Offerings and Simplify Reporting Requirements",
      "originalSummary": "The Securities and Exchange Commission today proposed amendments to its rules and forms governing registered offerings that are designed to increase efficiency, flexibility, and cost savings for public companies while maintaining robust investor…",
      "avatar": "S",
      "score": 81,
      "category": "equity",
      "horizon": "mid",
      "asset": "equity",
      "title": "美国 SEC 新闻稿更新：资本市场监管和公司风险",
      "summary": "美国 SEC 新闻稿发布与资本市场监管和公司风险相关的新信息，系统将其归入股票类影响因素，重点观察它对股票的传导。正式决策应结合原文链接、后续数据和价格确认。",
      "aiBrief": "AI速读：这条信息主要讲资本市场监管和公司风险，值得跟踪。它可能通过盈利预期、估值风险和资金偏好影响股票，需要和原文、价格反应以及后续数据一起确认。",
      "watchPoints": [
        "相关板块 ETF 和龙头股是否放量反应",
        "盈利预期或监管风险是否扩散",
        "股票是否出现同向价格确认",
        "同主题是否出现第二个一手信源确认"
      ],
      "tags": [
        "股票",
        "S级信源",
        "股票"
      ],
      "reason": "来自 美国 SEC 新闻稿 的高优先级信息，可能影响股票。评分综合信源等级、关键词命中、发布时间和影响资产范围。",
      "sourceRank": "S级",
      "absorbed": "尚未完全消化",
      "shortTerm": "短期观察该信息是否在股票价格中形成确认。",
      "midTerm": "中期结合后续数据和资金流，判断股票主线是否延续。",
      "longTerm": "长期意义取决于它是否改变利率、盈利、通胀或风险溢价的基准假设。",
      "decision": "仅作为研究和风控输入，不作为单独交易信号；等待价格、数据和信源交叉确认。"
    },
    {
      "id": "sec_press-sec-charges-21-individuals-with-alleged-wide-reachin-4da21510",
      "date": "5月6日",
      "time": "23:24",
      "sourceId": "sec_press",
      "source": "美国 SEC 新闻稿",
      "sourceUrl": "https://www.sec.gov/newsroom/press-releases/2026-44-sec-charges-21-individuals-alleged-wide-reaching-insider-trading-scheme",
      "sourceBrief": "资本市场监管、执法和披露风险的一手信源。",
      "originalTitle": "SEC Charges 21 Individuals With Alleged Wide-Reaching Insider Trading Scheme",
      "originalSummary": "The Securities and Exchange Commission today charged 21 individuals for their alleged involvement in a decade-long insider trading scheme that used information misappropriated from multiple global law firms and resulted in millions of dollars in illicit…",
      "avatar": "S",
      "score": 79,
      "category": "equity",
      "horizon": "mid",
      "asset": "equity",
      "title": "美国 SEC 新闻稿更新：资本市场监管和公司风险",
      "summary": "美国 SEC 新闻稿发布与资本市场监管和公司风险相关的新信息，系统将其归入股票类影响因素，重点观察它对股票的传导。正式决策应结合原文链接、后续数据和价格确认。",
      "aiBrief": "AI速读：这条信息主要讲资本市场监管和公司风险，值得跟踪。它可能通过盈利预期、估值风险和资金偏好影响股票，需要和原文、价格反应以及后续数据一起确认。",
      "watchPoints": [
        "相关板块 ETF 和龙头股是否放量反应",
        "盈利预期或监管风险是否扩散",
        "股票是否出现同向价格确认",
        "同主题是否出现第二个一手信源确认"
      ],
      "tags": [
        "股票",
        "S级信源",
        "股票"
      ],
      "reason": "来自 美国 SEC 新闻稿 的高优先级信息，可能影响股票。评分综合信源等级、关键词命中、发布时间和影响资产范围。",
      "sourceRank": "S级",
      "absorbed": "部分消化",
      "shortTerm": "短期观察该信息是否在股票价格中形成确认。",
      "midTerm": "中期结合后续数据和资金流，判断股票主线是否延续。",
      "longTerm": "长期意义取决于它是否改变利率、盈利、通胀或风险溢价的基准假设。",
      "decision": "仅作为研究和风控输入，不作为单独交易信号；等待价格、数据和信源交叉确认。"
    },
    {
      "id": "ft_home-trump-lashes-out-at-republicans-who-oppose-his-anti--f0e39e77",
      "date": "5月22日",
      "time": "18:41",
      "sourceId": "ft_home",
      "source": "Financial Times",
      "sourceUrl": "https://www.ft.com/content/bf9cf8d8-ace7-48f5-a0ce-35b4c89553cd",
      "sourceBrief": "国际高可信财经媒体，适合跟踪政策、企业、地缘和长期结构变化。",
      "originalTitle": "Trump lashes out at Republicans who oppose his ‘anti-weaponisation’ fund",
      "originalSummary": "President says senators who object to his $1.8bn fund for alleged victims of ‘lawfare’ are ‘screwing the Republican Party’",
      "avatar": "F",
      "score": 78,
      "category": "equity",
      "horizon": "mid",
      "asset": "equity",
      "title": "Financial Times观察：股票市场监管、盈利和资金流",
      "summary": "Financial Times报道了与股票市场监管、盈利和资金流相关的市场线索，系统将其归入股票类影响因素。它更适合帮助理解市场叙事和资金情绪，仍需用一手数据和价格反应验证。",
      "aiBrief": "AI速读：这是一条媒体解释源，主要讲股票市场监管、盈利和资金流，值得跟踪。它有助于理解市场正在交易什么叙事，但不能替代官方数据；需要观察股票是否给出价格确认。",
      "watchPoints": [
        "相关板块 ETF 和龙头股是否放量反应",
        "盈利预期或监管风险是否扩散",
        "股票是否出现同向价格确认",
        "同主题是否出现第二个一手信源确认"
      ],
      "tags": [
        "股票",
        "媒体解释源",
        "股票"
      ],
      "reason": "来自 Financial Times 的高优先级信息，可能影响股票。评分综合信源等级、关键词命中、发布时间和影响资产范围。",
      "sourceRank": "A级",
      "absorbed": "部分消化",
      "shortTerm": "短期观察该信息是否在股票价格中形成确认。",
      "midTerm": "中期结合后续数据和资金流，判断股票主线是否延续。",
      "longTerm": "长期意义取决于它是否改变利率、盈利、通胀或风险溢价的基准假设。",
      "decision": "仅作为研究和风控输入，不作为单独交易信号；等待价格、数据和信源交叉确认。"
    },
    {
      "id": "ft_home-if-you-think-you-understand-bonds-you-don-t-e850689b",
      "date": "5月22日",
      "time": "11:00",
      "sourceId": "ft_home",
      "source": "Financial Times",
      "sourceUrl": "https://www.ft.com/content/e7258e06-7be0-4578-80d1-994f27ba3c2b",
      "sourceBrief": "国际高可信财经媒体，适合跟踪政策、企业、地缘和长期结构变化。",
      "originalTitle": "If you think you understand bonds, you don’t",
      "originalSummary": "They’re too complex for me too — but here are five common traps to avoid",
      "avatar": "F",
      "score": 78,
      "category": "bond",
      "horizon": "mid",
      "asset": "bond equity fx gold",
      "title": "Financial Times观察：利率、债务和期限溢价",
      "summary": "Financial Times报道了与利率、债务和期限溢价相关的市场线索，系统将其归入债券类影响因素。它更适合帮助理解市场叙事和资金情绪，仍需用一手数据和价格反应验证。",
      "aiBrief": "AI速读：这是一条媒体解释源，主要讲利率、债务和期限溢价，值得跟踪。它有助于理解市场正在交易什么叙事，但不能替代官方数据；需要观察股票、债券、黄金、汇率是否给出价格确认。",
      "watchPoints": [
        "长端收益率是否突破近期区间",
        "财政融资或拍卖需求是否继续恶化",
        "股票、债券、黄金、汇率是否出现同向价格确认",
        "同主题是否出现第二个一手信源确认"
      ],
      "tags": [
        "债券",
        "媒体解释源",
        "股票、债券、黄金、汇率"
      ],
      "reason": "来自 Financial Times 的高优先级信息，可能影响股票、债券、黄金、汇率。评分综合信源等级、关键词命中、发布时间和影响资产范围。",
      "sourceRank": "A级",
      "absorbed": "部分消化",
      "shortTerm": "短期观察该信息是否在股票、债券、黄金、汇率价格中形成确认。",
      "midTerm": "中期结合后续数据和资金流，判断债券主线是否延续。",
      "longTerm": "长期意义取决于它是否改变利率、盈利、通胀或风险溢价的基准假设。",
      "decision": "仅作为研究和风控输入，不作为单独交易信号；等待价格、数据和信源交叉确认。"
    },
    {
      "id": "ft_home-trump-s-risky-military-options-to-break-iran-deadloc-ce4034ad",
      "date": "5月22日",
      "time": "10:34",
      "sourceId": "ft_home",
      "source": "Financial Times",
      "sourceUrl": "https://www.ft.com/content/dbfb7578-e9aa-426a-8c8c-a439f589fbc5",
      "sourceBrief": "国际高可信财经媒体，适合跟踪政策、企业、地缘和长期结构变化。",
      "originalTitle": "Trump’s risky military options to break Iran deadlock",
      "originalSummary": "From air strikes to a naval operation, the US president has no simple way to force Iran to yield",
      "avatar": "F",
      "score": 78,
      "category": "bond",
      "horizon": "mid",
      "asset": "bond equity fx gold",
      "title": "Financial Times观察：利率、债务和期限溢价",
      "summary": "Financial Times报道了与利率、债务和期限溢价相关的市场线索，系统将其归入债券类影响因素。它更适合帮助理解市场叙事和资金情绪，仍需用一手数据和价格反应验证。",
      "aiBrief": "AI速读：这是一条媒体解释源，主要讲利率、债务和期限溢价，值得跟踪。它有助于理解市场正在交易什么叙事，但不能替代官方数据；需要观察股票、债券、黄金、汇率是否给出价格确认。",
      "watchPoints": [
        "长端收益率是否突破近期区间",
        "财政融资或拍卖需求是否继续恶化",
        "股票、债券、黄金、汇率是否出现同向价格确认",
        "同主题是否出现第二个一手信源确认"
      ],
      "tags": [
        "债券",
        "媒体解释源",
        "股票、债券、黄金、汇率"
      ],
      "reason": "来自 Financial Times 的高优先级信息，可能影响股票、债券、黄金、汇率。评分综合信源等级、关键词命中、发布时间和影响资产范围。",
      "sourceRank": "A级",
      "absorbed": "部分消化",
      "shortTerm": "短期观察该信息是否在股票、债券、黄金、汇率价格中形成确认。",
      "midTerm": "中期结合后续数据和资金流，判断债券主线是否延续。",
      "longTerm": "长期意义取决于它是否改变利率、盈利、通胀或风险溢价的基准假设。",
      "decision": "仅作为研究和风控输入，不作为单独交易信号；等待价格、数据和信源交叉确认。"
    },
    {
      "id": "bis_stats-statistical-release-bis-international-banking-statis-5c6f8ac6",
      "date": "1月29日",
      "time": "09:45",
      "sourceId": "bis_stats",
      "source": "国际清算银行统计发布",
      "sourceUrl": "https://www.bis.org/statistics/rppb2601.htm",
      "sourceBrief": "全球流动性、跨境银行和杠杆周期的中长期监测来源。",
      "originalTitle": "Statistical release: BIS international banking statistics and global liquidity indicators at end-September 2025",
      "originalSummary": "Global cross-border bank claims expanded by $832 billion in the third quarter of 2025, reaching $45 trillion. The $730 billion Q3 2025 increase in cross-border bank credit was led by lending to borrowers in the United States ($284 billion); non-bank financial institutions (NBFIs) were a prominent counterparty globally, especially those in the United States ($157 billion). Cross-border bank credit to emerging Asia declined by 6% year on year, while that to emerging Europe, Africa and the Middle East, and Latin America grew by 24%, 17% and 6%, respectively. The BIS global liquidity indicators show that foreign currency credit in dollars grew by 7% year on year at end-Q3 2025 on the back of a weakening dollar. Foreign currency credit in euros grew 11% while that in yen contracted by 4%.",
      "avatar": "D",
      "score": 78,
      "category": "risk",
      "horizon": "short",
      "asset": "equity bond gold fx",
      "title": "国际清算银行统计发布更新：全球流动性和金融稳定",
      "summary": "国际清算银行统计发布发布与全球流动性和金融稳定相关的新信息，系统将其归入风险类影响因素，重点观察它对股票、债券、黄金、汇率的传导。正式决策应结合原文链接、后续数据和价格确认。",
      "aiBrief": "AI速读：这条信息主要讲全球流动性和金融稳定，值得跟踪。它可能通过波动率、信用利差和避险需求影响股票、债券、黄金、汇率，需要和原文、价格反应以及后续数据一起确认。",
      "watchPoints": [
        "VIX、信用利差和美元是否同时上行",
        "避险资产是否获得持续买盘",
        "股票、债券、黄金、汇率是否出现同向价格确认",
        "同主题是否出现第二个一手信源确认"
      ],
      "tags": [
        "风险",
        "A级信源",
        "股票、债券、黄金、汇率"
      ],
      "reason": "来自 国际清算银行统计发布 的高优先级信息，可能影响股票、债券、黄金、汇率。评分综合信源等级、关键词命中、发布时间和影响资产范围。",
      "sourceRank": "A级",
      "absorbed": "部分消化",
      "shortTerm": "短期观察该信息是否在股票、债券、黄金、汇率价格中形成确认。",
      "midTerm": "中期结合后续数据和资金流，判断风险主线是否延续。",
      "longTerm": "长期意义取决于它是否改变利率、盈利、通胀或风险溢价的基准假设。",
      "decision": "仅作为研究和风控输入，不作为单独交易信号；等待价格、数据和信源交叉确认。"
    },
    {
      "id": "bis_stats-otc-interest-rate-derivatives-turnover-in-april-2025-2d2fa27f",
      "date": "9月30日",
      "time": "09:45",
      "sourceId": "bis_stats",
      "source": "国际清算银行统计发布",
      "sourceUrl": "https://www.bis.org/statistics/rpfx25_ir.htm",
      "sourceBrief": "全球流动性、跨境银行和杠杆周期的中长期监测来源。",
      "originalTitle": "OTC interest rate derivatives turnover in April 2025",
      "originalSummary": "This statistical release concerns the IRD turnover part of the 2025 Triennial Survey that took place in April and involved central banks and other authorities in 52 jurisdictions.",
      "avatar": "D",
      "score": 76,
      "category": "macro",
      "horizon": "short",
      "asset": "equity bond gold fx",
      "title": "国际清算银行统计发布更新：利率政策和央行路径",
      "summary": "国际清算银行统计发布发布与利率政策和央行路径相关的新信息，系统将其归入宏观类影响因素，重点观察它对股票、债券、黄金、汇率的传导。正式决策应结合原文链接、后续数据和价格确认。",
      "aiBrief": "AI速读：这条信息主要讲利率政策和央行路径，值得跟踪。它可能通过利率预期、美元方向和估值折现率影响股票、债券、黄金、汇率，需要和原文、价格反应以及后续数据一起确认。",
      "watchPoints": [
        "美债收益率和美元是否同步反应",
        "降息或加息概率是否重新定价",
        "股票、债券、黄金、汇率是否出现同向价格确认",
        "同主题是否出现第二个一手信源确认"
      ],
      "tags": [
        "宏观",
        "A级信源",
        "股票、债券、黄金、汇率"
      ],
      "reason": "来自 国际清算银行统计发布 的高优先级信息，可能影响股票、债券、黄金、汇率。评分综合信源等级、关键词命中、发布时间和影响资产范围。",
      "sourceRank": "A级",
      "absorbed": "部分消化",
      "shortTerm": "短期观察该信息是否在股票、债券、黄金、汇率价格中形成确认。",
      "midTerm": "中期结合后续数据和资金流，判断宏观主线是否延续。",
      "longTerm": "长期意义取决于它是否改变利率、盈利、通胀或风险溢价的基准假设。",
      "decision": "仅作为研究和风控输入，不作为单独交易信号；等待价格、数据和信源交叉确认。"
    },
    {
      "id": "treasury_press-remarks-by-treasury-secretary-scott-bessent-before-t-8677dc29",
      "date": "5月22日",
      "time": "20:06",
      "sourceId": "treasury_press",
      "source": "美国财政部新闻稿",
      "sourceUrl": "https://home.treasury.gov/news/press-releases/sb0504",
      "sourceBrief": "财政、发债、制裁和跨境资金政策的官方来源，会影响美债、美元和风险偏好。",
      "originalTitle": "Remarks by Treasury Secretary Scott Bessent before the Brunswick School Commencement: The Life Within Reach, and the Life You Choose to Live",
      "originalSummary": "",
      "avatar": "T",
      "score": 76,
      "category": "bond",
      "horizon": "mid",
      "asset": "bond equity fx gold",
      "title": "美国财政部新闻稿更新：财政融资和美债供给",
      "summary": "美国财政部新闻稿发布与财政融资和美债供给相关的新信息，系统将其归入债券类影响因素，重点观察它对股票、债券、黄金、汇率的传导。正式决策应结合原文链接、后续数据和价格确认。",
      "aiBrief": "AI速读：这条信息主要讲财政融资和美债供给，值得跟踪。它可能通过收益率曲线、期限溢价和美元流动性影响股票、债券、黄金、汇率，需要和原文、价格反应以及后续数据一起确认。",
      "watchPoints": [
        "长端收益率是否突破近期区间",
        "财政融资或拍卖需求是否继续恶化",
        "股票、债券、黄金、汇率是否出现同向价格确认",
        "同主题是否出现第二个一手信源确认"
      ],
      "tags": [
        "债券",
        "S级信源",
        "股票、债券、黄金、汇率"
      ],
      "reason": "来自 美国财政部新闻稿 的高优先级信息，可能影响股票、债券、黄金、汇率。评分综合信源等级、关键词命中、发布时间和影响资产范围。",
      "sourceRank": "S级",
      "absorbed": "部分消化",
      "shortTerm": "短期观察该信息是否在股票、债券、黄金、汇率价格中形成确认。",
      "midTerm": "中期结合后续数据和资金流，判断债券主线是否延续。",
      "longTerm": "长期意义取决于它是否改变利率、盈利、通胀或风险溢价的基准假设。",
      "decision": "仅作为研究和风控输入，不作为单独交易信号；等待价格、数据和信源交叉确认。"
    },
    {
      "id": "treasury_press-remarks-by-secretary-of-the-treasury-scott-bessent-b-b650a25c",
      "date": "5月22日",
      "time": "20:06",
      "sourceId": "treasury_press",
      "source": "美国财政部新闻稿",
      "sourceUrl": "https://home.treasury.gov/news/press-releases/sb0500",
      "sourceBrief": "财政、发债、制裁和跨境资金政策的官方来源，会影响美债、美元和风险偏好。",
      "originalTitle": "Remarks by Secretary of the Treasury Scott Bessent Before the No Money for Terror Conference",
      "originalSummary": "",
      "avatar": "T",
      "score": 76,
      "category": "bond",
      "horizon": "mid",
      "asset": "bond equity fx gold",
      "title": "美国财政部新闻稿更新：财政融资和美债供给",
      "summary": "美国财政部新闻稿发布与财政融资和美债供给相关的新信息，系统将其归入债券类影响因素，重点观察它对股票、债券、黄金、汇率的传导。正式决策应结合原文链接、后续数据和价格确认。",
      "aiBrief": "AI速读：这条信息主要讲财政融资和美债供给，值得跟踪。它可能通过收益率曲线、期限溢价和美元流动性影响股票、债券、黄金、汇率，需要和原文、价格反应以及后续数据一起确认。",
      "watchPoints": [
        "长端收益率是否突破近期区间",
        "财政融资或拍卖需求是否继续恶化",
        "股票、债券、黄金、汇率是否出现同向价格确认",
        "同主题是否出现第二个一手信源确认"
      ],
      "tags": [
        "债券",
        "S级信源",
        "股票、债券、黄金、汇率"
      ],
      "reason": "来自 美国财政部新闻稿 的高优先级信息，可能影响股票、债券、黄金、汇率。评分综合信源等级、关键词命中、发布时间和影响资产范围。",
      "sourceRank": "S级",
      "absorbed": "部分消化",
      "shortTerm": "短期观察该信息是否在股票、债券、黄金、汇率价格中形成确认。",
      "midTerm": "中期结合后续数据和资金流，判断债券主线是否延续。",
      "longTerm": "长期意义取决于它是否改变利率、盈利、通胀或风险溢价的基准假设。",
      "decision": "仅作为研究和风控输入，不作为单独交易信号；等待价格、数据和信源交叉确认。"
    },
    {
      "id": "cnbc_markets-new-lawsuit-against-trump-s-doj-lawfare-fund-ca95414c",
      "date": "5月22日",
      "time": "19:56",
      "sourceId": "cnbc_markets",
      "source": "CNBC 市场新闻",
      "sourceUrl": "https://www.cnbc.com/2026/05/22/trump-doj-fund-republicans.html",
      "sourceBrief": "美国主流财经媒体，适合跟踪股市、科技股、政策交易和投资者情绪。",
      "originalTitle": "New lawsuit against Trump's DOJ 'lawfare' fund",
      "originalSummary": "President Trump droppped his $10 billion lawsuit against the IRS in exchange for the DOJ creating a $1.8 billion fund to compensate alleged \"lawfare\" victims.",
      "avatar": "N",
      "score": 76,
      "category": "equity",
      "horizon": "mid",
      "asset": "equity",
      "title": "CNBC 市场新闻观察：股票市场监管、盈利和资金流",
      "summary": "CNBC 市场新闻报道了与股票市场监管、盈利和资金流相关的市场线索，系统将其归入股票类影响因素。它更适合帮助理解市场叙事和资金情绪，仍需用一手数据和价格反应验证。",
      "aiBrief": "AI速读：这是一条媒体解释源，主要讲股票市场监管、盈利和资金流，值得跟踪。它有助于理解市场正在交易什么叙事，但不能替代官方数据；需要观察股票是否给出价格确认。",
      "watchPoints": [
        "相关板块 ETF 和龙头股是否放量反应",
        "盈利预期或监管风险是否扩散",
        "股票是否出现同向价格确认",
        "同主题是否出现第二个一手信源确认"
      ],
      "tags": [
        "股票",
        "媒体解释源",
        "股票"
      ],
      "reason": "来自 CNBC 市场新闻 的高优先级信息，可能影响股票。评分综合信源等级、关键词命中、发布时间和影响资产范围。",
      "sourceRank": "A级",
      "absorbed": "部分消化",
      "shortTerm": "短期观察该信息是否在股票价格中形成确认。",
      "midTerm": "中期结合后续数据和资金流，判断股票主线是否延续。",
      "longTerm": "长期意义取决于它是否改变利率、盈利、通胀或风险溢价的基准假设。",
      "decision": "仅作为研究和风控输入，不作为单独交易信号；等待价格、数据和信源交叉确认。"
    },
    {
      "id": "cnbc_markets-trump-said-he-d-remember-companies-that-didn-t-apply-348d99d2",
      "date": "5月22日",
      "time": "16:56",
      "sourceId": "cnbc_markets",
      "source": "CNBC 市场新闻",
      "sourceUrl": "https://www.cnbc.com/2026/05/22/trump-tariff-refunds-walmart-home-depot-target-apply.html",
      "sourceBrief": "美国主流财经媒体，适合跟踪股市、科技股、政策交易和投资者情绪。",
      "originalTitle": "Trump said he'd 'remember' companies that didn't apply for tariff refunds. Many of them are anyway",
      "originalSummary": "Walmart confirmed to CNBC it has sought a tariff refund and plans to use any money it receives back to invest in lower prices for shoppers.",
      "avatar": "N",
      "score": 76,
      "category": "equity",
      "horizon": "mid",
      "asset": "equity",
      "title": "CNBC 市场新闻观察：通胀压力和实际利率",
      "summary": "CNBC 市场新闻报道了与通胀压力和实际利率相关的市场线索，系统将其归入股票类影响因素。它更适合帮助理解市场叙事和资金情绪，仍需用一手数据和价格反应验证。",
      "aiBrief": "AI速读：这是一条媒体解释源，主要讲通胀压力和实际利率，值得跟踪。它有助于理解市场正在交易什么叙事，但不能替代官方数据；需要观察股票是否给出价格确认。",
      "watchPoints": [
        "相关板块 ETF 和龙头股是否放量反应",
        "盈利预期或监管风险是否扩散",
        "股票是否出现同向价格确认",
        "同主题是否出现第二个一手信源确认"
      ],
      "tags": [
        "股票",
        "媒体解释源",
        "股票"
      ],
      "reason": "来自 CNBC 市场新闻 的高优先级信息，可能影响股票。评分综合信源等级、关键词命中、发布时间和影响资产范围。",
      "sourceRank": "A级",
      "absorbed": "部分消化",
      "shortTerm": "短期观察该信息是否在股票价格中形成确认。",
      "midTerm": "中期结合后续数据和资金流，判断股票主线是否延续。",
      "longTerm": "长期意义取决于它是否改变利率、盈利、通胀或风险溢价的基准假设。",
      "decision": "仅作为研究和风控输入，不作为单独交易信号；等待价格、数据和信源交叉确认。"
    },
    {
      "id": "cnbc_markets-wall-street-thinks-imax-is-ripe-for-a-sale-here-s-wh-c7e1bab2",
      "date": "5月22日",
      "time": "16:26",
      "sourceId": "cnbc_markets",
      "source": "CNBC 市场新闻",
      "sourceUrl": "https://www.cnbc.com/2026/05/22/imax-sale-talks-potential-buyers-wall-street-analysts.html",
      "sourceBrief": "美国主流财经媒体，适合跟踪股市、科技股、政策交易和投资者情绪。",
      "originalTitle": "Wall Street thinks IMAX is ripe for a sale. Here's who could buy it",
      "originalSummary": "A source told CNBC that IMAX has held \"preliminary talks\" through intermediaries, but no official pitches have been made by the company.",
      "avatar": "N",
      "score": 76,
      "category": "equity",
      "horizon": "mid",
      "asset": "equity",
      "title": "CNBC 市场新闻观察：股票市场监管、盈利和资金流",
      "summary": "CNBC 市场新闻报道了与股票市场监管、盈利和资金流相关的市场线索，系统将其归入股票类影响因素。它更适合帮助理解市场叙事和资金情绪，仍需用一手数据和价格反应验证。",
      "aiBrief": "AI速读：这是一条媒体解释源，主要讲股票市场监管、盈利和资金流，值得跟踪。它有助于理解市场正在交易什么叙事，但不能替代官方数据；需要观察股票是否给出价格确认。",
      "watchPoints": [
        "相关板块 ETF 和龙头股是否放量反应",
        "盈利预期或监管风险是否扩散",
        "股票是否出现同向价格确认",
        "同主题是否出现第二个一手信源确认"
      ],
      "tags": [
        "股票",
        "媒体解释源",
        "股票"
      ],
      "reason": "来自 CNBC 市场新闻 的高优先级信息，可能影响股票。评分综合信源等级、关键词命中、发布时间和影响资产范围。",
      "sourceRank": "A级",
      "absorbed": "部分消化",
      "shortTerm": "短期观察该信息是否在股票价格中形成确认。",
      "midTerm": "中期结合后续数据和资金流，判断股票主线是否延续。",
      "longTerm": "长期意义取决于它是否改变利率、盈利、通胀或风险溢价的基准假设。",
      "decision": "仅作为研究和风控输入，不作为单独交易信号；等待价格、数据和信源交叉确认。"
    },
    {
      "id": "census_indicators-manufacturing-and-trade-inventories-and-sales-63a12612",
      "date": "5月14日",
      "time": "14:00",
      "sourceId": "census_indicators",
      "source": "美国人口普查局经济指标",
      "sourceUrl": "https://www.census.gov/mtis/index.html",
      "sourceBrief": "零售、库存、贸易和制造业等实体经济指标的官方来源。",
      "originalTitle": "Manufacturing and Trade Inventories and Sales",
      "originalSummary": "U.S. total business end-of-month inventories for March 2026 were $2,709.7 billion, up 0.9 percent (+/- 0.1 percent) from last month. U.S. total business sales were $2,059.2 billion, up 2.1 percent (+/- 0.1 percent) from last month. March 2026: +0.9 % Change in Inventories February 2026 (r): +0.4 % Change in Inventories",
      "avatar": "C",
      "score": 76,
      "category": "macro",
      "horizon": "short",
      "asset": "equity bond gold fx",
      "title": "美国人口普查局经济指标更新：消费需求和企业收入",
      "summary": "美国人口普查局经济指标发布与消费需求和企业收入相关的新信息，系统将其归入宏观类影响因素，重点观察它对股票、债券、黄金、汇率的传导。正式决策应结合原文链接、后续数据和价格确认。",
      "aiBrief": "AI速读：这条信息主要讲消费需求和企业收入，值得跟踪。它可能通过利率预期、美元方向和估值折现率影响股票、债券、黄金、汇率，需要和原文、价格反应以及后续数据一起确认。",
      "watchPoints": [
        "美债收益率和美元是否同步反应",
        "降息或加息概率是否重新定价",
        "股票、债券、黄金、汇率是否出现同向价格确认",
        "同主题是否出现第二个一手信源确认"
      ],
      "tags": [
        "宏观",
        "S级信源",
        "股票、债券、黄金、汇率"
      ],
      "reason": "来自 美国人口普查局经济指标 的高优先级信息，可能影响股票、债券、黄金、汇率。评分综合信源等级、关键词命中、发布时间和影响资产范围。",
      "sourceRank": "S级",
      "absorbed": "部分消化",
      "shortTerm": "短期观察该信息是否在股票、债券、黄金、汇率价格中形成确认。",
      "midTerm": "中期结合后续数据和资金流，判断宏观主线是否延续。",
      "longTerm": "长期意义取决于它是否改变利率、盈利、通胀或风险溢价的基准假设。",
      "decision": "仅作为研究和风控输入，不作为单独交易信号；等待价格、数据和信源交叉确认。"
    },
    {
      "id": "bis_stats-bis-global-liquidity-indicators-at-end-december-2025-2fbdcfb6",
      "date": "4月30日",
      "time": "09:50",
      "sourceId": "bis_stats",
      "source": "国际清算银行统计发布",
      "sourceUrl": "https://www.bis.org/statistics/gli2604.htm",
      "sourceBrief": "全球流动性、跨境银行和杠杆周期的中长期监测来源。",
      "originalTitle": "BIS global liquidity indicators at end-December 2025",
      "originalSummary": "The BIS global liquidity indicators show that foreign currency credit in US dollars and euros continued to grow robustly, both globally and in EMDEs.",
      "avatar": "D",
      "score": 76,
      "category": "risk",
      "horizon": "short",
      "asset": "equity bond gold fx",
      "title": "国际清算银行统计发布更新：全球流动性和金融稳定",
      "summary": "国际清算银行统计发布发布与全球流动性和金融稳定相关的新信息，系统将其归入风险类影响因素，重点观察它对股票、债券、黄金、汇率的传导。正式决策应结合原文链接、后续数据和价格确认。",
      "aiBrief": "AI速读：这条信息主要讲全球流动性和金融稳定，值得跟踪。它可能通过波动率、信用利差和避险需求影响股票、债券、黄金、汇率，需要和原文、价格反应以及后续数据一起确认。",
      "watchPoints": [
        "VIX、信用利差和美元是否同时上行",
        "避险资产是否获得持续买盘",
        "股票、债券、黄金、汇率是否出现同向价格确认",
        "同主题是否出现第二个一手信源确认"
      ],
      "tags": [
        "风险",
        "A级信源",
        "股票、债券、黄金、汇率"
      ],
      "reason": "来自 国际清算银行统计发布 的高优先级信息，可能影响股票、债券、黄金、汇率。评分综合信源等级、关键词命中、发布时间和影响资产范围。",
      "sourceRank": "A级",
      "absorbed": "部分消化",
      "shortTerm": "短期观察该信息是否在股票、债券、黄金、汇率价格中形成确认。",
      "midTerm": "中期结合后续数据和资金流，判断风险主线是否延续。",
      "longTerm": "长期意义取决于它是否改变利率、盈利、通胀或风险溢价的基准假设。",
      "decision": "仅作为研究和风控输入，不作为单独交易信号；等待价格、数据和信源交叉确认。"
    },
    {
      "id": "marketwatch_top-ibm-could-be-a-big-winner-as-quantum-computing-moves-6011789c",
      "date": "5月22日",
      "time": "19:58",
      "sourceId": "marketwatch_top",
      "source": "MarketWatch 头条",
      "sourceUrl": "https://www.marketwatch.com/story/ibm-could-be-a-big-winner-as-quantum-computing-moves-out-of-the-science-fiction-realm-1eb74952?mod=mw_rss_topstories",
      "sourceBrief": "面向投资者的市场新闻源，适合观察美股、基金和个人投资者叙事。",
      "originalTitle": "IBM could be a big winner as quantum computing moves out of the science-fiction realm",
      "originalSummary": "The new era of quantum computing will happen, IBM says, as it sees nothing fundamentally to stop it.",
      "avatar": "M",
      "score": 75,
      "category": "equity",
      "horizon": "mid",
      "asset": "equity",
      "title": "MarketWatch 头条观察：股票市场监管、盈利和资金流",
      "summary": "MarketWatch 头条报道了与股票市场监管、盈利和资金流相关的市场线索，系统将其归入股票类影响因素。它更适合帮助理解市场叙事和资金情绪，仍需用一手数据和价格反应验证。",
      "aiBrief": "AI速读：这是一条媒体解释源，主要讲股票市场监管、盈利和资金流，值得跟踪。它有助于理解市场正在交易什么叙事，但不能替代官方数据；需要观察股票是否给出价格确认。",
      "watchPoints": [
        "相关板块 ETF 和龙头股是否放量反应",
        "盈利预期或监管风险是否扩散",
        "股票是否出现同向价格确认",
        "同主题是否出现第二个一手信源确认"
      ],
      "tags": [
        "股票",
        "媒体解释源",
        "股票"
      ],
      "reason": "来自 MarketWatch 头条 的高优先级信息，可能影响股票。评分综合信源等级、关键词命中、发布时间和影响资产范围。",
      "sourceRank": "A级",
      "absorbed": "部分消化",
      "shortTerm": "短期观察该信息是否在股票价格中形成确认。",
      "midTerm": "中期结合后续数据和资金流，判断股票主线是否延续。",
      "longTerm": "长期意义取决于它是否改变利率、盈利、通胀或风险溢价的基准假设。",
      "decision": "仅作为研究和风控输入，不作为单独交易信号；等待价格、数据和信源交叉确认。"
    },
    {
      "id": "marketwatch_top-more-20-somethings-are-moving-in-with-their-parents--b683a115",
      "date": "5月22日",
      "time": "19:44",
      "sourceId": "marketwatch_top",
      "source": "MarketWatch 头条",
      "sourceUrl": "https://www.marketwatch.com/story/is-your-college-grad-moving-back-home-how-to-help-them-build-savings-and-protect-your-retirement-4a5fc109?mod=mw_rss_topstories",
      "sourceBrief": "面向投资者的市场新闻源，适合观察美股、基金和个人投资者叙事。",
      "originalTitle": "More 20-somethings are moving in with their parents. Here’s how they can build savings — without bankrupting mom and dad",
      "originalSummary": "As the class of 2026 looks toward the future after securing their diplomas, some are preparing to move from their dorm room back to their childhood bedroom.",
      "avatar": "M",
      "score": 75,
      "category": "equity",
      "horizon": "mid",
      "asset": "equity",
      "title": "MarketWatch 头条观察：资本市场监管和公司风险",
      "summary": "MarketWatch 头条报道了与资本市场监管和公司风险相关的市场线索，系统将其归入股票类影响因素。它更适合帮助理解市场叙事和资金情绪，仍需用一手数据和价格反应验证。",
      "aiBrief": "AI速读：这是一条媒体解释源，主要讲资本市场监管和公司风险，值得跟踪。它有助于理解市场正在交易什么叙事，但不能替代官方数据；需要观察股票是否给出价格确认。",
      "watchPoints": [
        "相关板块 ETF 和龙头股是否放量反应",
        "盈利预期或监管风险是否扩散",
        "股票是否出现同向价格确认",
        "同主题是否出现第二个一手信源确认"
      ],
      "tags": [
        "股票",
        "媒体解释源",
        "股票"
      ],
      "reason": "来自 MarketWatch 头条 的高优先级信息，可能影响股票。评分综合信源等级、关键词命中、发布时间和影响资产范围。",
      "sourceRank": "A级",
      "absorbed": "部分消化",
      "shortTerm": "短期观察该信息是否在股票价格中形成确认。",
      "midTerm": "中期结合后续数据和资金流，判断股票主线是否延续。",
      "longTerm": "长期意义取决于它是否改变利率、盈利、通胀或风险溢价的基准假设。",
      "decision": "仅作为研究和风控输入，不作为单独交易信号；等待价格、数据和信源交叉确认。"
    },
    {
      "id": "marketwatch_top-this-2008-train-wreck-oil-scenario-could-unfold-if-h-45e6e43f",
      "date": "5月22日",
      "time": "19:40",
      "sourceId": "marketwatch_top",
      "source": "MarketWatch 头条",
      "sourceUrl": "https://www.marketwatch.com/story/this-2008-train-wreck-oil-scenario-could-unfold-if-hormuz-isnt-opened-by-end-of-august-75b74bb1?mod=mw_rss_topstories",
      "sourceBrief": "面向投资者的市场新闻源，适合观察美股、基金和个人投资者叙事。",
      "originalTitle": "This 2008 ‘train wreck’ oil scenario could unfold if Hormuz isn’t opened by end of August",
      "originalSummary": "There’s a new warning from the commodity market about the risks of a delayed reopening of the Strait of Hormuz.",
      "avatar": "M",
      "score": 75,
      "category": "commodity",
      "horizon": "short",
      "asset": "commodity equity bond",
      "title": "MarketWatch 头条观察：能源供需和通胀传导",
      "summary": "MarketWatch 头条报道了与能源供需和通胀传导相关的市场线索，系统将其归入商品类影响因素。它更适合帮助理解市场叙事和资金情绪，仍需用一手数据和价格反应验证。",
      "aiBrief": "AI速读：这是一条媒体解释源，主要讲能源供需和通胀传导，值得跟踪。它有助于理解市场正在交易什么叙事，但不能替代官方数据；需要观察股票、债券、商品是否给出价格确认。",
      "watchPoints": [
        "库存、供给和现货价格是否同向变化",
        "通胀预期是否被重新抬升",
        "股票、债券、商品是否出现同向价格确认",
        "同主题是否出现第二个一手信源确认"
      ],
      "tags": [
        "商品",
        "媒体解释源",
        "股票、债券、商品"
      ],
      "reason": "来自 MarketWatch 头条 的高优先级信息，可能影响股票、债券、商品。评分综合信源等级、关键词命中、发布时间和影响资产范围。",
      "sourceRank": "A级",
      "absorbed": "部分消化",
      "shortTerm": "短期观察该信息是否在股票、债券、商品价格中形成确认。",
      "midTerm": "中期结合后续数据和资金流，判断商品主线是否延续。",
      "longTerm": "长期意义取决于它是否改变利率、盈利、通胀或风险溢价的基准假设。",
      "decision": "仅作为研究和风控输入，不作为单独交易信号；等待价格、数据和信源交叉确认。"
    },
    {
      "id": "guardian_business-the-guardian-view-on-britain-s-coming-energy-shock-m-db117740",
      "date": "5月22日",
      "time": "16:59",
      "sourceId": "guardian_business",
      "source": "Guardian Business",
      "sourceUrl": "https://www.theguardian.com/commentisfree/2026/may/22/the-guardian-view-on-britains-coming-energy-shock-mini-measures-wont-suffice",
      "sourceBrief": "英国商业与政策新闻源，适合补充欧洲经济、监管和社会政策影响。",
      "originalTitle": "The Guardian view on Britain’s coming energy shock: mini-measures won’t suffice | Editorial",
      "originalSummary": "Consumer giveaways may soften the blow from the the war on Iran. But Britain’s vulnerability demands deeper state intervention and a faster transition Rachel Reeves’s announcement of a series of cost of living measures this week shows a government trying to prove it still has agency and relevance. The VAT cuts on summer attractions such as theme parks and soft-play centres, free bus rides for the under-16s in England and reduced import tariffs on food are politically useful, but they do not fundamentally alter the UK’s exposure to imported energy shocks. This is a mini-budget, with the emphasis on the mini. The inflationary impact of the Iran crisis, however, will be substantial. That is why the chancellor is moving into crisis-management mode with industrial resilience funds and thinly veiled threats to tax profiteers . But it is unlikely to be enough. The repercussions from the closure of the strait of Hormuz are reviving the need for more radical state fiscal intervention. Ms Reeves moved pre-emptively because the energy regulator is next week expected to announce that energy bills are likely to rise by £209 to £1,850 a year for a typical dual-fuel household from July. That is ​an increase of 13% on the current £1,641 ​annual bill. It will be a direct hit to household disposable incomes – and Labour’s central political claim that the cost of living crisis is easing on its watch. Worse may still be to come. If households absorb a summer rise in bills and then face costs rising again before winter, the government risks a return to the levels of financial anxiety felt after the Russian invasion of Ukraine. Do you have an opinion on the issues raised in this article? If you would like to submit a response of up to 300 words by email to be considered for publication in our letters section, please click here . Continue reading...",
      "avatar": "G",
      "score": 75,
      "category": "equity",
      "horizon": "mid",
      "asset": "equity",
      "title": "Guardian Business观察：通胀压力和实际利率",
      "summary": "Guardian Business报道了与通胀压力和实际利率相关的市场线索，系统将其归入股票类影响因素。它更适合帮助理解市场叙事和资金情绪，仍需用一手数据和价格反应验证。",
      "aiBrief": "AI速读：这是一条媒体解释源，主要讲通胀压力和实际利率，值得跟踪。它有助于理解市场正在交易什么叙事，但不能替代官方数据；需要观察股票是否给出价格确认。",
      "watchPoints": [
        "相关板块 ETF 和龙头股是否放量反应",
        "盈利预期或监管风险是否扩散",
        "股票是否出现同向价格确认",
        "同主题是否出现第二个一手信源确认"
      ],
      "tags": [
        "股票",
        "媒体解释源",
        "股票"
      ],
      "reason": "来自 Guardian Business 的高优先级信息，可能影响股票。评分综合信源等级、关键词命中、发布时间和影响资产范围。",
      "sourceRank": "B级",
      "absorbed": "部分消化",
      "shortTerm": "短期观察该信息是否在股票价格中形成确认。",
      "midTerm": "中期结合后续数据和资金流，判断股票主线是否延续。",
      "longTerm": "长期意义取决于它是否改变利率、盈利、通胀或风险溢价的基准假设。",
      "decision": "仅作为研究和风控输入，不作为单独交易信号；等待价格、数据和信源交叉确认。"
    },
    {
      "id": "bbc_business-borrowing-in-april-hit-highest-level-since-covid-fa99a2e6",
      "date": "5月22日",
      "time": "14:07",
      "sourceId": "bbc_business",
      "source": "BBC Business",
      "sourceUrl": "https://www.bbc.com/news/articles/ce9py7nx8j4o?at_medium=RSS&at_campaign=rss",
      "sourceBrief": "国际商业新闻源，适合补充宏观、消费、企业和英国/欧洲风险线索。",
      "originalTitle": "Borrowing in April hit highest level since Covid",
      "originalSummary": "Borrowing was higher than expected last month and retail sales fell as fuel prices surged.",
      "avatar": "B",
      "score": 75,
      "category": "macro",
      "horizon": "short",
      "asset": "equity bond gold fx",
      "title": "BBC Business观察：通胀压力和实际利率",
      "summary": "BBC Business报道了与通胀压力和实际利率相关的市场线索，系统将其归入宏观类影响因素。它更适合帮助理解市场叙事和资金情绪，仍需用一手数据和价格反应验证。",
      "aiBrief": "AI速读：这是一条媒体解释源，主要讲通胀压力和实际利率，值得跟踪。它有助于理解市场正在交易什么叙事，但不能替代官方数据；需要观察股票、债券、黄金、汇率是否给出价格确认。",
      "watchPoints": [
        "美债收益率和美元是否同步反应",
        "降息或加息概率是否重新定价",
        "股票、债券、黄金、汇率是否出现同向价格确认",
        "同主题是否出现第二个一手信源确认"
      ],
      "tags": [
        "宏观",
        "媒体解释源",
        "股票、债券、黄金、汇率"
      ],
      "reason": "来自 BBC Business 的高优先级信息，可能影响股票、债券、黄金、汇率。评分综合信源等级、关键词命中、发布时间和影响资产范围。",
      "sourceRank": "B级",
      "absorbed": "部分消化",
      "shortTerm": "短期观察该信息是否在股票、债券、黄金、汇率价格中形成确认。",
      "midTerm": "中期结合后续数据和资金流，判断宏观主线是否延续。",
      "longTerm": "长期意义取决于它是否改变利率、盈利、通胀或风险溢价的基准假设。",
      "decision": "仅作为研究和风控输入，不作为单独交易信号；等待价格、数据和信源交叉确认。"
    },
    {
      "id": "guardian_business-uk-borrows-more-than-forecast-in-april-as-inflation--dc5c1ea5",
      "date": "5月22日",
      "time": "08:55",
      "sourceId": "guardian_business",
      "source": "Guardian Business",
      "sourceUrl": "https://www.theguardian.com/business/2026/may/22/uk-borrowed-bigger-april-inflation-benefits-bill",
      "sourceBrief": "英国商业与政策新闻源，适合补充欧洲经济、监管和社会政策影响。",
      "originalTitle": "UK borrows more than forecast in April as inflation adds to benefits bill",
      "originalSummary": "The £24.3bn figure comes amid rising cost of pensions as bond market jitters take monthly debt interest to £10.3bn The UK borrowed more than expected in April as high inflation drove up the cost of pensions and benefits, with concern over the Iran war and political uncertainty adding to debt costs. The Office for National Statistics (ONS) said public sector net borrowing – the difference between government spending and income – was £24.3bn in April 2026, £4.9bn higher than in April 2025. Continue reading...",
      "avatar": "G",
      "score": 75,
      "category": "bond",
      "horizon": "mid",
      "asset": "bond equity fx gold",
      "title": "Guardian Business观察：通胀压力和实际利率",
      "summary": "Guardian Business报道了与通胀压力和实际利率相关的市场线索，系统将其归入债券类影响因素。它更适合帮助理解市场叙事和资金情绪，仍需用一手数据和价格反应验证。",
      "aiBrief": "AI速读：这是一条媒体解释源，主要讲通胀压力和实际利率，值得跟踪。它有助于理解市场正在交易什么叙事，但不能替代官方数据；需要观察股票、债券、黄金、汇率是否给出价格确认。",
      "watchPoints": [
        "长端收益率是否突破近期区间",
        "财政融资或拍卖需求是否继续恶化",
        "股票、债券、黄金、汇率是否出现同向价格确认",
        "同主题是否出现第二个一手信源确认"
      ],
      "tags": [
        "债券",
        "媒体解释源",
        "股票、债券、黄金、汇率"
      ],
      "reason": "来自 Guardian Business 的高优先级信息，可能影响股票、债券、黄金、汇率。评分综合信源等级、关键词命中、发布时间和影响资产范围。",
      "sourceRank": "B级",
      "absorbed": "部分消化",
      "shortTerm": "短期观察该信息是否在股票、债券、黄金、汇率价格中形成确认。",
      "midTerm": "中期结合后续数据和资金流，判断债券主线是否延续。",
      "longTerm": "长期意义取决于它是否改变利率、盈利、通胀或风险溢价的基准假设。",
      "decision": "仅作为研究和风控输入，不作为单独交易信号；等待价格、数据和信源交叉确认。"
    },
    {
      "id": "census_indicators-u-s-international-trade-in-goods-and-services-59a6ab80",
      "date": "5月5日",
      "time": "12:30",
      "sourceId": "census_indicators",
      "source": "美国人口普查局经济指标",
      "sourceUrl": "https://www.census.gov/foreign-trade/index.html",
      "sourceBrief": "零售、库存、贸易和制造业等实体经济指标的官方来源。",
      "originalTitle": "U.S. International Trade in Goods and Services",
      "originalSummary": "The nation's international trade deficit in goods and services increased to $60.3 billion in March from $57.8 billion in February (revised), as imports increased more than exports. March 2026: 4.4° % Change February 2026 (r): 5.7° % Change",
      "avatar": "C",
      "score": 74,
      "category": "macro",
      "horizon": "short",
      "asset": "equity bond gold fx",
      "title": "美国人口普查局经济指标更新：财政融资和美债供给",
      "summary": "美国人口普查局经济指标发布与财政融资和美债供给相关的新信息，系统将其归入宏观类影响因素，重点观察它对股票、债券、黄金、汇率的传导。正式决策应结合原文链接、后续数据和价格确认。",
      "aiBrief": "AI速读：这条信息主要讲财政融资和美债供给，值得跟踪。它可能通过利率预期、美元方向和估值折现率影响股票、债券、黄金、汇率，需要和原文、价格反应以及后续数据一起确认。",
      "watchPoints": [
        "美债收益率和美元是否同步反应",
        "降息或加息概率是否重新定价",
        "股票、债券、黄金、汇率是否出现同向价格确认",
        "同主题是否出现第二个一手信源确认"
      ],
      "tags": [
        "宏观",
        "S级信源",
        "股票、债券、黄金、汇率"
      ],
      "reason": "来自 美国人口普查局经济指标 的高优先级信息，可能影响股票、债券、黄金、汇率。评分综合信源等级、关键词命中、发布时间和影响资产范围。",
      "sourceRank": "S级",
      "absorbed": "部分消化",
      "shortTerm": "短期观察该信息是否在股票、债券、黄金、汇率价格中形成确认。",
      "midTerm": "中期结合后续数据和资金流，判断宏观主线是否延续。",
      "longTerm": "长期意义取决于它是否改变利率、盈利、通胀或风险溢价的基准假设。",
      "decision": "仅作为研究和风控输入，不作为单独交易信号；等待价格、数据和信源交叉确认。"
    }
  ]
}
